{"viewId":1616411979757,"height":2000,"width":2000,"backgroundOverlayColor":"#00000000","backgroundColor":"#FFE9E9E9","version":9,"subViews":[{"viewId":1616411984664,"layerFullLocked":false,"layerHidden":false,"layerLocked":"true","maskRoundRectRadius":0,"border":"0","borderColor":"#FF000000","opacity":"1.0","rotateAngle":"90.0","backgroundColor":"#00000000","xPoint":"1197.222","yPoint":"1080.5554","selected":"false","tiltX":0,"tiltY":0,"layoutParamsHeight":"-2","layoutParamsWidth":"-2","rootLayoutHeight":"940","rootLayoutWidth":"750","textPadding":0,"bitmapFilePath":".images\/1616411984664.imagitorImage","viewType":"imageView","zoomScale":"0.7200001","scaleType":"CENTER_CROP","flipHorizontal":1,"flipVertical":1,"tintColor":"#00000000","maskMode":0,"shadow":{"shadowRadius":0,"shadowColor":"#FF444444","shadowDist":15,"shadowAngle":45}},{"viewId":1616413327081,"layerFullLocked":false,"layerHidden":false,"layerLocked":"false","maskRoundRectRadius":0,"border":"0","borderColor":"#00000000","opacity":"1.0","rotateAngle":"90.0","backgroundColor":"#00000000","xPoint":"0.0","yPoint":"0.0","selected":"false","tiltX":0,"tiltY":0,"layoutParamsHeight":"-1","layoutParamsWidth":"-1","rootLayoutHeight":"2000","rootLayoutWidth":"2000","textPadding":0,"viewType":"shapeView2","zoomScale":"0.7200001","shapeLayers":[{"shapeType":"shapePolygon","shapeVertices":[{"xPoint":2057.6826171875,"yPoint":1398,"shapeBezChanged":false,"shapeVertBezPrev":{"xPoint":1070.8836669921875,"yPoint":821.3914794921875,"shapeBezChanged":false},"shapeVertBezNext":{"xPoint":3044.475830078125,"yPoint":821.3914794921875,"shapeBezChanged":false}},{"xPoint":5018.35791015625,"yPoint":-332,"shapeBezChanged":false,"shapeVertBezPrev":{"xPoint":4031.564453125,"yPoint":244.60931396484375,"shapeBezChanged":false},"shapeVertBezNext":{"xPoint":3044.7744140625,"yPoint":-332,"shapeBezChanged":false}},{"xPoint":-903,"yPoint":-332,"shapeBezChanged":false,"shapeVertBezPrev":{"xPoint":1070.5894775390625,"yPoint":-332,"shapeBezChanged":false},"shapeVertBezNext":{"xPoint":83.79443359375,"yPoint":244.60931396484375,"shapeBezChanged":false}}],"shapeVerticesVer":1,"fillColor":"#FF393939","borderColor":"#FF000000","border":0,"joinType":1,"rotateAngle":0,"cornerRadius":0,"shadow":{"shadowRadius":0,"shadowColor":"#FF444444","shadowDist":15,"shadowAngle":45}}],"flipHorizontal":1,"flipVertical":1},{"viewId":1616412124221,"layerFullLocked":false,"layerHidden":false,"layerLocked":"false","maskRoundRectRadius":0,"border":"0","borderColor":"#00000000","opacity":"1.0","rotateAngle":"90.0","backgroundColor":"#00000000","xPoint":"0.0","yPoint":"0.0","selected":"false","tiltX":0,"tiltY":0,"layoutParamsHeight":"-1","layoutParamsWidth":"-1","rootLayoutHeight":"2000","rootLayoutWidth":"2000","textPadding":0,"viewType":"shapeView2","zoomScale":"0.7200001","shapeLayers":[{"shapeType":"shapePolygon","shapeVertices":[{"xPoint":1944.1885986328125,"yPoint":1749.255615234375,"shapeBezChanged":false,"shapeVertBezPrev":{"xPoint":1741.8748779296875,"yPoint":1868.2437744140625,"shapeBezChanged":false},"shapeVertBezNext":{"xPoint":2146.501953125,"yPoint":1868.2437744140625,"shapeBezChanged":false}},{"xPoint":2551.18798828125,"yPoint":2106.255615234375,"shapeBezChanged":false,"shapeVertBezPrev":{"xPoint":2348.87548828125,"yPoint":1987.2674560546875,"shapeBezChanged":false},"shapeVertBezNext":{"xPoint":2146.5625,"yPoint":2106.255615234375,"shapeBezChanged":false}},{"xPoint":1337.187744140625,"yPoint":2106.255615234375,"shapeBezChanged":false,"shapeVertBezPrev":{"xPoint":1741.8143310546875,"yPoint":2106.255615234375,"shapeBezChanged":false},"shapeVertBezNext":{"xPoint":1539.5010986328125,"yPoint":1987.2674560546875,"shapeBezChanged":false}}],"shapeVerticesVer":1,"fillColor":"#FF393939","borderColor":"#FF000000","border":0,"joinType":1,"rotateAngle":0,"cornerRadius":0,"shadow":{"shadowRadius":0,"shadowColor":"#FF444444","shadowDist":15,"shadowAngle":45}}],"flipHorizontal":1,"flipVertical":1},{"viewId":1616412202471,"layerFullLocked":false,"layerHidden":false,"layerLocked":"false","maskRoundRectRadius":0,"border":"0","borderColor":"#00000000","opacity":"1.0","rotateAngle":"90.0","backgroundColor":"#00000000","xPoint":"0.0","yPoint":"0.0","selected":"false","tiltX":0,"tiltY":0,"layoutParamsHeight":"-1","layoutParamsWidth":"-1","rootLayoutHeight":"2000","rootLayoutWidth":"2000","textPadding":0,"viewType":"shapeView2","zoomScale":"0.7200001","shapeLayers":[{"shapeType":"shapePolygon","shapeVertices":[{"xPoint":1196.846923828125,"yPoint":1749.255615234375,"shapeBezChanged":false,"shapeVertBezPrev":{"xPoint":994.3665161132812,"yPoint":1868.2437744140625,"shapeBezChanged":false},"shapeVertBezNext":{"xPoint":1399.325927734375,"yPoint":1868.2437744140625,"shapeBezChanged":false}},{"xPoint":1804.345947265625,"yPoint":2106.255615234375,"shapeBezChanged":false,"shapeVertBezPrev":{"xPoint":1601.866455078125,"yPoint":1987.2674560546875,"shapeBezChanged":false},"shapeVertBezNext":{"xPoint":1399.38720703125,"yPoint":2106.255615234375,"shapeBezChanged":false}},{"xPoint":589.345947265625,"yPoint":2106.255615234375,"shapeBezChanged":false,"shapeVertBezPrev":{"xPoint":994.3057250976562,"yPoint":2106.255615234375,"shapeBezChanged":false},"shapeVertBezNext":{"xPoint":791.8258666992188,"yPoint":1987.2674560546875,"shapeBezChanged":false}}],"shapeVerticesVer":1,"fillColor":"#FF393939","borderColor":"#FF000000","border":0,"joinType":1,"rotateAngle":0,"cornerRadius":0,"shadow":{"shadowRadius":0,"shadowColor":"#FF444444","shadowDist":15,"shadowAngle":45}}],"flipHorizontal":1,"flipVertical":1},{"viewId":1616412437827,"layerFullLocked":false,"layerHidden":false,"layerLocked":"false","maskRoundRectRadius":0,"border":"0","borderColor":"#00000000","opacity":"1.0","rotateAngle":"90.0","backgroundColor":"#00000000","xPoint":"0.0","yPoint":"0.0","selected":"false","tiltX":0,"tiltY":0,"layoutParamsHeight":"-1","layoutParamsWidth":"-1","rootLayoutHeight":"2000","rootLayoutWidth":"2000","textPadding":0,"viewType":"shapeView2","zoomScale":"0.7200001","shapeLayers":[{"shapeType":"shapePolygon","shapeVertices":[{"xPoint":815.7499389648438,"yPoint":1554,"shapeBezChanged":false,"shapeVertBezPrev":{"xPoint":490.1995849609375,"yPoint":1366.186279296875,"shapeBezChanged":false},"shapeVertBezNext":{"xPoint":1141.3006591796875,"yPoint":1366.186279296875,"shapeBezChanged":false}},{"xPoint":1792.4998779296875,"yPoint":990.5006103515625,"shapeBezChanged":false,"shapeVertBezPrev":{"xPoint":1466.9476318359375,"yPoint":1178.3148193359375,"shapeBezChanged":false},"shapeVertBezNext":{"xPoint":1792.4998779296875,"yPoint":614.8717041015625,"shapeBezChanged":false}},{"xPoint":1792.4998779296875,"yPoint":-136.5,"shapeBezChanged":false,"shapeVertBezPrev":{"xPoint":1792.4998779296875,"yPoint":239.12957763671875,"shapeBezChanged":false},"shapeVertBezNext":{"xPoint":1466.9476318359375,"yPoint":-324.314208984375,"shapeBezChanged":false}},{"xPoint":815.7499389648438,"yPoint":-700,"shapeBezChanged":false,"shapeVertBezPrev":{"xPoint":1141.3006591796875,"yPoint":-512.1853637695312,"shapeBezChanged":false},"shapeVertBezNext":{"xPoint":490.1995849609375,"yPoint":-512.1853637695312,"shapeBezChanged":false}},{"xPoint":-161,"yPoint":-136.5,"shapeBezChanged":false,"shapeVertBezPrev":{"xPoint":164.55130004882812,"yPoint":-324.314208984375,"shapeBezChanged":false},"shapeVertBezNext":{"xPoint":-161,"yPoint":239.12957763671875,"shapeBezChanged":false}},{"xPoint":-161,"yPoint":990.5001220703125,"shapeBezChanged":false,"shapeVertBezPrev":{"xPoint":-161,"yPoint":614.8717041015625,"shapeBezChanged":false},"shapeVertBezNext":{"xPoint":164.55130004882812,"yPoint":1178.3148193359375,"shapeBezChanged":false}}],"shapeVerticesVer":1,"fillColor":"#FFFEBB62","borderColor":"#FF000000","border":0,"joinType":1,"rotateAngle":0,"cornerRadius":0,"shadow":{"shadowRadius":0,"shadowColor":"#FF444444","shadowDist":15,"shadowAngle":45}}],"flipHorizontal":1,"flipVertical":1},{"viewId":1616413921686,"layerFullLocked":false,"layerHidden":false,"layerLocked":"false","maskRoundRectRadius":30,"border":"0","borderColor":"#00000000","opacity":"1.0","rotateAngle":"90.0","backgroundColor":"#00000000","xPoint":"244.44435","yPoint":"-13.888884","selected":"false","tiltX":0,"tiltY":0,"layoutParamsHeight":"-2","layoutParamsWidth":"-2","rootLayoutHeight":"1234","rootLayoutWidth":"1229","textPadding":0,"viewType":"textView","zoomScale":"0.7200001","text":"حسنِ ازل ہے پیدا تاروں کی دلبری میں\nجس طرح عکسِ گُل ہو شبنم کی آرسی میں\nآئینِ نو سے ڈرنا، طرزِ کُہن پہ اَڑنا\nمنزل یہی کٹھن ہے قوموں کی زندگی میں","textAlignment":"textCenterAlignment","textVerticalAlignment":"textCenterVerticalAlignment","typeFaceName":"Mehr Nastaliq Web","typeFaceType":"urdu","textSize":"46.857143","textSizeSP":164,"textColor":"#FF111111","flipHorizontal":"1.0","flipVertical":"1.0","stroke":"0.0","strokeColor":"#FFFFFFFF","shadowRadius":"0.0","shadowColor":"#FF444444","shadowX":"5.0","shadowY":"5.0","lineSpacing":"1.0","wordSpacing":0.0010000000474974513,"wordArc":0,"textBold":false,"textItalic":false,"textUnderline":false,"textEmboss":false,"textEmbossFull":false,"zeroSpans":[{"spanStart":4,"spanEnd":5},{"spanStart":8,"spanEnd":9},{"spanStart":11,"spanEnd":12},{"spanStart":16,"spanEnd":17},{"spanStart":22,"spanEnd":23},{"spanStart":25,"spanEnd":26},{"spanStart":31,"spanEnd":32},{"spanStart":38,"spanEnd":39},{"spanStart":42,"spanEnd":43},{"spanStart":47,"spanEnd":48},{"spanStart":51,"spanEnd":52},{"spanStart":54,"spanEnd":55},{"spanStart":59,"spanEnd":60},{"spanStart":62,"spanEnd":63},{"spanStart":67,"spanEnd":68},{"spanStart":77,"spanEnd":78},{"spanStart":80,"spanEnd":81},{"spanStart":83,"spanEnd":84},{"spanStart":89,"spanEnd":90},{"spanStart":94,"spanEnd":95},{"spanStart":99,"spanEnd":100},{"spanStart":102,"spanEnd":103},{"spanStart":113,"spanEnd":114},{"spanStart":117,"spanEnd":118},{"spanStart":122,"spanEnd":123},{"spanStart":125,"spanEnd":126},{"spanStart":131,"spanEnd":132},{"spanStart":134,"spanEnd":135},{"spanStart":140,"spanEnd":141}],"harfSpans":[{"xPoint":0,"yPoint":0,"textSize":140,"spanSizePerc":100,"spanStart":0,"spanEnd":4,"spanFormt":{}},{"xPoint":10.006950378417969,"yPoint":-22.415557861328125,"textSize":140,"spanSizePerc":100,"spanStart":5,"spanEnd":6,"spanFormt":{}},{"xPoint":7.1049346923828125,"yPoint":-15.41070556640625,"textSize":140,"spanSizePerc":100,"spanStart":6,"spanEnd":7,"spanFormt":{}},{"xPoint":5.7039642333984375,"yPoint":-1.3009033203125,"textSize":140,"spanSizePerc":100,"spanStart":7,"spanEnd":8,"spanFormt":{}},{"xPoint":38.82695770263672,"yPoint":-2.5017318725585938,"textSize":140,"spanSizePerc":100,"spanStart":9,"spanEnd":11,"spanFormt":{}},{"xPoint":29.820716857910156,"yPoint":-5.7039642333984375,"textSize":140,"spanSizePerc":100,"spanStart":12,"spanEnd":15,"spanFormt":{}},{"xPoint":31.62195587158203,"yPoint":-26.718555450439453,"textSize":140,"spanSizePerc":100,"spanStart":15,"spanEnd":16,"spanFormt":{}},{"xPoint":19.01319122314453,"yPoint":-12.408615112304688,"textSize":140,"spanSizePerc":100,"spanStart":17,"spanEnd":19,"spanFormt":{}},{"xPoint":12.208465576171875,"yPoint":-7.62939453125E-6,"textSize":140,"spanSizePerc":100,"spanStart":19,"spanEnd":20,"spanFormt":{}},{"xPoint":28.219589233398438,"yPoint":-47.43293380737305,"textSize":140,"spanSizePerc":100,"spanStart":20,"spanEnd":21,"spanFormt":{}},{"xPoint":13.909652709960938,"yPoint":-8.305763244628906,"textSize":140,"spanSizePerc":100,"spanStart":21,"spanEnd":22,"spanFormt":{}},{"xPoint":11.307853698730469,"yPoint":0.20014190673828125,"textSize":140,"spanSizePerc":100,"spanStart":23,"spanEnd":25,"spanFormt":{}},{"xPoint":32.822792053222656,"yPoint":-67.44684600830078,"textSize":140,"spanSizePerc":100,"spanStart":26,"spanEnd":27,"spanFormt":{}},{"xPoint":15.61083984375,"yPoint":-4.503120422363281,"textSize":140,"spanSizePerc":100,"spanStart":27,"spanEnd":30,"spanFormt":{}},{"xPoint":35.62474060058594,"yPoint":-23.216102600097656,"textSize":140,"spanSizePerc":100,"spanStart":30,"spanEnd":31,"spanFormt":{}},{"xPoint":25.6177978515625,"yPoint":-14.009727478027344,"textSize":140,"spanSizePerc":100,"spanStart":32,"spanEnd":36,"spanFormt":{}},{"xPoint":0,"yPoint":0,"textSize":140,"spanSizePerc":100,"spanStart":36,"spanEnd":38,"spanFormt":{}},{"xPoint":28.719947814941406,"yPoint":-49.63445281982422,"textSize":140,"spanSizePerc":100,"spanStart":39,"spanEnd":41,"spanFormt":{}},{"xPoint":33.42321014404297,"yPoint":-0.20013427734375,"textSize":140,"spanSizePerc":100,"spanStart":41,"spanEnd":42,"spanFormt":{}},{"xPoint":44.93119812011719,"yPoint":4.403053283691406,"textSize":140,"spanSizePerc":100,"spanStart":43,"spanEnd":47,"spanFormt":{}},{"xPoint":43.029876708984375,"yPoint":7.1049346923828125,"textSize":140,"spanSizePerc":100,"spanStart":48,"spanEnd":51,"spanFormt":{}},{"xPoint":49.63446807861328,"yPoint":-14.610153198242188,"textSize":140,"spanSizePerc":100,"spanStart":52,"spanEnd":54,"spanFormt":{}},{"xPoint":51.535789489746094,"yPoint":-2.40167236328125,"textSize":140,"spanSizePerc":100,"spanStart":55,"spanEnd":59,"spanFormt":{}},{"xPoint":26.118133544921875,"yPoint":-0.800567626953125,"textSize":140,"spanSizePerc":100,"spanStart":60,"spanEnd":62,"spanFormt":{}},{"xPoint":18.813072204589844,"yPoint":-8.305770874023438,"textSize":140,"spanSizePerc":100,"spanStart":63,"spanEnd":64,"spanFormt":{}},{"xPoint":14.910346984863281,"yPoint":-4.302986145019531,"textSize":140,"spanSizePerc":100,"spanStart":64,"spanEnd":65,"spanFormt":{}},{"xPoint":17.812362670898438,"yPoint":7.62939453125E-6,"textSize":140,"spanSizePerc":100,"spanStart":65,"spanEnd":67,"spanFormt":{}},{"xPoint":9.306465148925781,"yPoint":-6.504524230957031,"textSize":140,"spanSizePerc":100,"spanStart":68,"spanEnd":72,"spanFormt":{}},{"xPoint":0,"yPoint":0,"textSize":140,"spanSizePerc":100,"spanStart":72,"spanEnd":73,"spanFormt":{}},{"xPoint":5.703956604003906,"yPoint":0.10007476806640625,"textSize":140,"spanSizePerc":100,"spanStart":73,"spanEnd":77,"spanFormt":{}},{"xPoint":19.31340789794922,"yPoint":-42.72966003417969,"textSize":140,"spanSizePerc":100,"spanStart":78,"spanEnd":80,"spanFormt":{}},{"xPoint":29.020156860351562,"yPoint":1.00067138671875,"textSize":140,"spanSizePerc":100,"spanStart":81,"spanEnd":83,"spanFormt":{}},{"xPoint":18.883888244628906,"yPoint":-10.651962280273438,"textSize":140,"spanSizePerc":100,"spanStart":84,"spanEnd":85,"spanFormt":{}},{"xPoint":11.808197021484375,"yPoint":-8.305770874023438,"textSize":140,"spanSizePerc":100,"spanStart":85,"spanEnd":86,"spanFormt":{}},{"xPoint":12.418296813964844,"yPoint":-21.114654541015625,"textSize":140,"spanSizePerc":100,"spanStart":86,"spanEnd":88,"spanFormt":{}},{"xPoint":3.6436920166015625,"yPoint":-6.7046051025390625,"textSize":140,"spanSizePerc":100,"spanStart":88,"spanEnd":89,"spanFormt":{}},{"xPoint":0,"yPoint":0,"textSize":140,"spanSizePerc":100,"spanStart":90,"spanEnd":92,"spanFormt":{}},{"xPoint":10.107009887695312,"yPoint":-0.7004776000976562,"textSize":140,"spanSizePerc":100,"spanStart":92,"spanEnd":93,"spanFormt":{}},{"xPoint":10.107009887695312,"yPoint":-0.7004776000976562,"textSize":140,"spanSizePerc":100,"spanStart":93,"spanEnd":94,"spanFormt":{}},{"xPoint":7.405143737792969,"yPoint":1.400970458984375,"textSize":140,"spanSizePerc":100,"spanStart":95,"spanEnd":99,"spanFormt":{}},{"xPoint":8.956222534179688,"yPoint":-22.215423583984375,"textSize":140,"spanSizePerc":100,"spanStart":100,"spanEnd":102,"spanFormt":{}},{"xPoint":0,"yPoint":0,"textSize":140,"spanSizePerc":100,"spanStart":103,"spanEnd":104,"spanFormt":{}},{"xPoint":-2.3015975952148438,"yPoint":0.4002685546875,"textSize":140,"spanSizePerc":100,"spanStart":104,"spanEnd":106,"spanFormt":{}},{"xPoint":3.1851348876953125,"yPoint":-2.6292572021484375,"textSize":140,"spanSizePerc":100,"spanStart":106,"spanEnd":108,"spanFormt":{}},{"xPoint":0,"yPoint":0,"textSize":140,"spanSizePerc":100,"spanStart":108,"spanEnd":109,"spanFormt":{}},{"xPoint":0,"yPoint":0,"textSize":140,"spanSizePerc":100,"spanStart":109,"spanEnd":112,"spanFormt":{}},{"xPoint":6.050994873046875,"yPoint":-2.4580230712890625,"textSize":140,"spanSizePerc":100,"spanStart":112,"spanEnd":113,"spanFormt":{}},{"xPoint":7.9045867919921875,"yPoint":3.38671875,"textSize":140,"spanSizePerc":100,"spanStart":114,"spanEnd":117,"spanFormt":{}},{"xPoint":41.84223937988281,"yPoint":1.135528564453125,"textSize":140,"spanSizePerc":100,"spanStart":118,"spanEnd":122,"spanFormt":{}},{"xPoint":83.43693542480469,"yPoint":-83.39402770996094,"textSize":140,"spanSizePerc":100,"spanStart":123,"spanEnd":125,"spanFormt":{}},{"xPoint":41.242279052734375,"yPoint":-5.790374755859375,"textSize":140,"spanSizePerc":100,"spanStart":126,"spanEnd":128,"spanFormt":{}},{"xPoint":33.773475646972656,"yPoint":-4.303009033203125,"textSize":140,"spanSizePerc":100,"spanStart":128,"spanEnd":130,"spanFormt":{}},{"xPoint":22.865867614746094,"yPoint":-5.00347900390625,"textSize":140,"spanSizePerc":100,"spanStart":130,"spanEnd":131,"spanFormt":{}},{"xPoint":16.43505096435547,"yPoint":-0.0509490966796875,"textSize":140,"spanSizePerc":100,"spanStart":132,"spanEnd":134,"spanFormt":{}},{"xPoint":37.25029754638672,"yPoint":-61.81193542480469,"textSize":140,"spanSizePerc":100,"spanStart":135,"spanEnd":136,"spanFormt":{}},{"xPoint":21.45720672607422,"yPoint":-29.634292602539062,"textSize":140,"spanSizePerc":100,"spanStart":136,"spanEnd":138,"spanFormt":{}},{"xPoint":11.20794677734375,"yPoint":3.0191497802734375,"textSize":140,"spanSizePerc":100,"spanStart":138,"spanEnd":140,"spanFormt":{}},{"xPoint":15.010425567626953,"yPoint":-4.252960205078125,"textSize":140,"spanSizePerc":100,"spanStart":141,"spanEnd":144,"spanFormt":{}}],"textDirection":4,"textTextureScale":0},{"viewId":1616414731660,"layerFullLocked":false,"layerHidden":false,"layerLocked":"false","maskRoundRectRadius":30,"border":"0","borderColor":"#00000000","opacity":"1.0","rotateAngle":"90.0","backgroundColor":"#00000000","xPoint":"322.2221","yPoint":"1370.8329","selected":"false","tiltX":0,"tiltY":0,"layoutParamsHeight":"-2","layoutParamsWidth":"-2","rootLayoutHeight":"509","rootLayoutWidth":"846","textPadding":0,"viewType":"textView","zoomScale":"0.7200001","text":"اقبـال","textAlignment":"textCenterAlignment","textVerticalAlignment":"textCenterVerticalAlignment","typeFaceName":"gandhara-suls-regular","typeFaceType":"urdu","textSize":"68.0","textSizeSP":238,"textColor":"#FF000000","flipHorizontal":"1.0","flipVertical":"1.0","stroke":"16.0","strokeColor":"#FFFFFFFF","shadowRadius":"0.0","shadowColor":"#FF6B6B6B","shadowX":"1.0","shadowY":"4.0","lineSpacing":"1.0","wordSpacing":0.0010000000474974513,"wordArc":0,"textBold":false,"textItalic":false,"textUnderline":false,"textEmboss":false,"textEmbossFull":false,"zeroSpans":[],"harfSpans":[],"textDirection":4,"textTextureScale":0},{"viewId":1615547862965,"layerFullLocked":false,"layerHidden":false,"layerLocked":"false","maskRoundRectRadius":0,"border":"0","borderColor":"#00000000","opacity":"1.0","rotateAngle":"90.0","backgroundColor":"#00000000","xPoint":"0.0","yPoint":"0.0","selected":"false","tiltX":0,"tiltY":0,"layoutParamsHeight":"-1","layoutParamsWidth":"-1","rootLayoutHeight":"2000","rootLayoutWidth":"2000","textPadding":0,"viewType":"shapeView2","zoomScale":"0.7200001","shapeLayers":[{"shapeType":"shapePolygon","shapeVertices":[{"xPoint":121.40739440917969,"yPoint":1483.27734375,"shapeBezChanged":false,"shapeVertBezPrev":{"xPoint":121.40739440917969,"yPoint":1410.6181640625,"shapeBezChanged":false},"shapeVertBezNext":{"xPoint":194.06698608398438,"yPoint":1483.27734375,"shapeBezChanged":false}},{"xPoint":339.40740966796875,"yPoint":1483.27734375,"shapeBezChanged":false,"shapeVertBezPrev":{"xPoint":266.747802734375,"yPoint":1483.27734375,"shapeBezChanged":false},"shapeVertBezNext":{"xPoint":339.40740966796875,"yPoint":1410.6181640625,"shapeBezChanged":false}},{"xPoint":339.40740966796875,"yPoint":1265.27734375,"shapeBezChanged":false,"shapeVertBezPrev":{"xPoint":339.40740966796875,"yPoint":1337.936767578125,"shapeBezChanged":false},"shapeVertBezNext":{"xPoint":266.747802734375,"yPoint":1265.27734375,"shapeBezChanged":false}},{"xPoint":121.40739440917969,"yPoint":1265.27734375,"shapeBezChanged":false,"shapeVertBezPrev":{"xPoint":194.06698608398438,"yPoint":1265.27734375,"shapeBezChanged":false},"shapeVertBezNext":{"xPoint":121.40739440917969,"yPoint":1337.936767578125,"shapeBezChanged":false}}],"shapeVerticesVer":1,"fillColor":"#FFC6C6C6","borderColor":"#FF000000","border":0,"joinType":1,"rotateAngle":0,"cornerRadius":72,"shadow":{"shadowRadius":0,"shadowColor":"#FF444444","shadowDist":15,"shadowAngle":45}}],"flipHorizontal":1,"flipVertical":1},{"viewId":1607103914736,"layerFullLocked":false,"layerHidden":false,"layerLocked":"false","maskRoundRectRadius":0,"border":"0","borderColor":"#00000000","opacity":"1.0","rotateAngle":"90.0","backgroundColor":"#00000000","xPoint":"0.0","yPoint":"0.0","selected":"false","tiltX":0,"tiltY":0,"layoutParamsHeight":"-1","layoutParamsWidth":"-1","rootLayoutHeight":"2000","rootLayoutWidth":"2000","textPadding":0,"viewType":"shapeView2","zoomScale":"0.7200001","shapeLayers":[{"shapeType":"shapePen","shapeVertices":[{"xPoint":230.55191040039062,"yPoint":1283.71435546875,"shapeBezChanged":false,"shapeVertBezNext":{"xPoint":231.77232360839844,"yPoint":1283.71435546875,"shapeBezChanged":false}},{"xPoint":234.2134246826172,"yPoint":1283.71435546875,"shapeBezChanged":false,"shapeVertBezPrev":{"xPoint":232.99302673339844,"yPoint":1283.71435546875,"shapeBezChanged":false},"shapeVertBezNext":{"xPoint":233.87725830078125,"yPoint":1328.544189453125,"shapeBezChanged":true}},{"xPoint":270.5519104003906,"yPoint":1377.8314208984375,"shapeBezChanged":false,"shapeVertBezPrev":{"xPoint":248.9229736328125,"yPoint":1355.55615234375,"shapeBezChanged":true},"shapeVertBezNext":{"xPoint":257.9036560058594,"yPoint":1396.856201171875,"shapeBezChanged":true}},{"xPoint":254.43138122558594,"yPoint":1433.71435546875,"shapeBezChanged":false,"shapeVertBezPrev":{"xPoint":254.4451446533203,"yPoint":1405.5133056640625,"shapeBezChanged":true},"shapeVertBezNext":{"xPoint":246.47239685058594,"yPoint":1433.71435546875,"shapeBezChanged":false}},{"xPoint":230.55191040039062,"yPoint":1433.71435546875,"shapeBezChanged":false,"shapeVertBezPrev":{"xPoint":238.51104736328125,"yPoint":1433.71435546875,"shapeBezChanged":false},"shapeVertBezNext":{"xPoint":230.55191040039062,"yPoint":1422.726318359375,"shapeBezChanged":false}},{"xPoint":230.55191040039062,"yPoint":1400.747314453125,"shapeBezChanged":false,"shapeVertBezPrev":{"xPoint":230.55191040039062,"yPoint":1411.735107421875,"shapeBezChanged":false},"shapeVertBezNext":{"xPoint":238.36721801757812,"yPoint":1399.411865234375,"shapeBezChanged":true}},{"xPoint":243.92445373535156,"yPoint":1385.087890625,"shapeBezChanged":false,"shapeVertBezPrev":{"xPoint":243.9208984375,"yPoint":1393.642333984375,"shapeBezChanged":true},"shapeVertBezNext":{"xPoint":244.4751739501953,"yPoint":1376.50537109375,"shapeBezChanged":true}},{"xPoint":230.55191040039062,"yPoint":1369.4287109375,"shapeBezChanged":false,"shapeVertBezPrev":{"xPoint":238.0473175048828,"yPoint":1370.000732421875,"shapeBezChanged":true},"shapeVertBezNext":{"xPoint":230.55191040039062,"yPoint":1340.860107421875,"shapeBezChanged":false}},{"xPoint":230.55191040039062,"yPoint":1283.71435546875,"shapeBezChanged":false,"shapeVertBezPrev":{"xPoint":230.55191040039062,"yPoint":1312.282958984375,"shapeBezChanged":false}}],"shapeVerticesVer":1,"fillColor":"#FF000000","borderColor":"#EB000000","border":0,"joinType":1,"rotateAngle":0,"cornerRadius":0,"shadow":{"shadowRadius":0,"shadowColor":"#FF444444","shadowDist":15,"shadowAngle":45}}],"flipHorizontal":1,"flipVertical":1},{"viewId":1607104566042,"layerFullLocked":false,"layerHidden":false,"layerLocked":"false","maskRoundRectRadius":0,"border":"0","borderColor":"#00000000","opacity":"1.0","rotateAngle":"90.0","backgroundColor":"#00000000","xPoint":"0.0","yPoint":"0.0","selected":"false","tiltX":0,"tiltY":0,"layoutParamsHeight":"-1","layoutParamsWidth":"-1","rootLayoutHeight":"2000","rootLayoutWidth":"2000","textPadding":0,"viewType":"shapeView2","zoomScale":"0.7200001","shapeLayers":[{"shapeType":"shapePen","shapeVertices":[{"xPoint":227.39260864257812,"yPoint":1283.71435546875,"shapeBezChanged":false,"shapeVertBezNext":{"xPoint":226.17221069335938,"yPoint":1283.71435546875,"shapeBezChanged":false}},{"xPoint":223.73109436035156,"yPoint":1283.71435546875,"shapeBezChanged":false,"shapeVertBezPrev":{"xPoint":224.95150756835938,"yPoint":1283.71435546875,"shapeBezChanged":false},"shapeVertBezNext":{"xPoint":224.0672607421875,"yPoint":1328.544189453125,"shapeBezChanged":true}},{"xPoint":187.39260864257812,"yPoint":1377.8314208984375,"shapeBezChanged":false,"shapeVertBezPrev":{"xPoint":209.02154541015625,"yPoint":1355.55615234375,"shapeBezChanged":true},"shapeVertBezNext":{"xPoint":200.04086303710938,"yPoint":1396.856201171875,"shapeBezChanged":true}},{"xPoint":203.5131378173828,"yPoint":1433.71435546875,"shapeBezChanged":false,"shapeVertBezPrev":{"xPoint":203.49937438964844,"yPoint":1405.5133056640625,"shapeBezChanged":true},"shapeVertBezNext":{"xPoint":211.4721221923828,"yPoint":1433.71435546875,"shapeBezChanged":false}},{"xPoint":227.39260864257812,"yPoint":1433.71435546875,"shapeBezChanged":false,"shapeVertBezPrev":{"xPoint":219.4334716796875,"yPoint":1433.71435546875,"shapeBezChanged":false},"shapeVertBezNext":{"xPoint":227.39260864257812,"yPoint":1422.726318359375,"shapeBezChanged":false}},{"xPoint":227.39260864257812,"yPoint":1400.747314453125,"shapeBezChanged":false,"shapeVertBezPrev":{"xPoint":227.39260864257812,"yPoint":1411.735107421875,"shapeBezChanged":false},"shapeVertBezNext":{"xPoint":219.57730102539062,"yPoint":1399.411865234375,"shapeBezChanged":true}},{"xPoint":214.0200653076172,"yPoint":1385.087890625,"shapeBezChanged":false,"shapeVertBezPrev":{"xPoint":214.02362060546875,"yPoint":1393.642333984375,"shapeBezChanged":true},"shapeVertBezNext":{"xPoint":213.4691925048828,"yPoint":1376.50537109375,"shapeBezChanged":true}},{"xPoint":227.39260864257812,"yPoint":1369.4287109375,"shapeBezChanged":false,"shapeVertBezPrev":{"xPoint":219.89718627929688,"yPoint":1370.000732421875,"shapeBezChanged":true},"shapeVertBezNext":{"xPoint":227.39260864257812,"yPoint":1340.860107421875,"shapeBezChanged":false}},{"xPoint":227.39260864257812,"yPoint":1283.71435546875,"shapeBezChanged":false,"shapeVertBezPrev":{"xPoint":227.39260864257812,"yPoint":1312.282958984375,"shapeBezChanged":false}}],"shapeVerticesVer":1,"fillColor":"#FF000000","borderColor":"#EB000000","border":0,"joinType":1,"rotateAngle":0,"cornerRadius":0,"shadow":{"shadowRadius":0,"shadowColor":"#FF444444","shadowDist":15,"shadowAngle":45}}],"flipHorizontal":1,"flipVertical":1},{"viewId":1607104600773,"layerFullLocked":false,"layerHidden":false,"layerLocked":"false","maskRoundRectRadius":0,"border":"0","borderColor":"#00000000","opacity":"1.0","rotateAngle":"90.0","backgroundColor":"#00000000","xPoint":"0.0","yPoint":"0.0","selected":"false","tiltX":0,"tiltY":0,"layoutParamsHeight":"-1","layoutParamsWidth":"-1","rootLayoutHeight":"2000","rootLayoutWidth":"2000","textPadding":0,"viewType":"shapeView2","zoomScale":"0.7200001","shapeLayers":[{"shapeType":"shapePolygon","shapeVertices":[{"xPoint":203.40774536132812,"yPoint":1464.672119140625,"shapeBezChanged":false,"shapeVertBezPrev":{"xPoint":203.40774536132812,"yPoint":1455.339599609375,"shapeBezChanged":false},"shapeVertBezNext":{"xPoint":220.73934936523438,"yPoint":1464.672119140625,"shapeBezChanged":false}},{"xPoint":255.40774536132812,"yPoint":1464.672119140625,"shapeBezChanged":false,"shapeVertBezPrev":{"xPoint":238.07614135742188,"yPoint":1464.672119140625,"shapeBezChanged":false},"shapeVertBezNext":{"xPoint":255.40774536132812,"yPoint":1455.339599609375,"shapeBezChanged":false}},{"xPoint":255.40774536132812,"yPoint":1436.672119140625,"shapeBezChanged":false,"shapeVertBezPrev":{"xPoint":255.40774536132812,"yPoint":1446.0045166015625,"shapeBezChanged":false},"shapeVertBezNext":{"xPoint":238.07614135742188,"yPoint":1436.672119140625,"shapeBezChanged":false}},{"xPoint":203.40774536132812,"yPoint":1436.672119140625,"shapeBezChanged":false,"shapeVertBezPrev":{"xPoint":220.73934936523438,"yPoint":1436.672119140625,"shapeBezChanged":false},"shapeVertBezNext":{"xPoint":203.40774536132812,"yPoint":1446.0045166015625,"shapeBezChanged":false}}],"shapeVerticesVer":1,"fillColor":"#FF000000","borderColor":"#FF000000","border":0,"joinType":1,"rotateAngle":0,"cornerRadius":0,"shadow":{"shadowRadius":0,"shadowColor":"#FF444444","shadowDist":15,"shadowAngle":45}}],"flipHorizontal":1,"flipVertical":1},{"viewId":1615547921477,"layerFullLocked":false,"layerHidden":false,"layerLocked":"false","maskRoundRectRadius":29,"border":"0","borderColor":"#00000000","opacity":"1.0","rotateAngle":"90.0","backgroundColor":"#00000000","xPoint":"42.8074","yPoint":"1484.581","selected":"false","tiltX":0,"tiltY":0,"layoutParamsHeight":"-2","layoutParamsWidth":"-2","rootLayoutHeight":"90","rootLayoutWidth":"374","textPadding":0,"viewType":"textView","zoomScale":"0.7200001","text":"IMAGITOR","textAlignment":"textCenterAlignment","textVerticalAlignment":"textTopAlignment","typeFaceName":"Prompt-Regular","typeFaceType":"all","textSize":"16.857143","textSizeSP":59,"textColor":"#FF111111","flipHorizontal":"1.0","flipVertical":"1.0","stroke":"0.0","strokeColor":"#FF696969","shadowRadius":"0.0","shadowColor":"#FF444444","shadowX":"5.0","shadowY":"5.0","lineSpacing":"1.0","wordSpacing":0.0010000000474974513,"wordArc":0,"textBold":false,"textItalic":false,"textUnderline":false,"textEmboss":false,"textEmbossFull":false,"zeroSpans":[],"harfSpans":[],"textDirection":1,"textTextureScale":0},{"viewId":1615547961894,"layerFullLocked":false,"layerHidden":false,"layerLocked":"false","maskRoundRectRadius":29,"border":"0","borderColor":"#00000000","opacity":"1.0","rotateAngle":"90.0","backgroundColor":"#00000000","xPoint":"12.499995","yPoint":"1551.0","selected":"false","tiltX":0,"tiltY":0,"layoutParamsHeight":"-2","layoutParamsWidth":"-2","rootLayoutHeight":"106","rootLayoutWidth":"436","textPadding":0,"viewType":"textView","zoomScale":"0.7200001","text":"اردو ڈیزائن ایپ","textAlignment":"textCenterAlignment","textVerticalAlignment":"textTopAlignment","typeFaceName":"NotoSansArabic-Light","typeFaceType":"urdu","textSize":"14.0","textSizeSP":49,"textColor":"#FF111111","flipHorizontal":"1.0","flipVertical":"1.0","stroke":"0.0","strokeColor":"#FF696969","shadowRadius":"0.0","shadowColor":"#FF444444","shadowX":"5.0","shadowY":"5.0","lineSpacing":"1.0","wordSpacing":0.0010000000474974513,"wordArc":0,"textBold":false,"textItalic":false,"textUnderline":false,"textEmboss":false,"textEmbossFull":false,"zeroSpans":[],"harfSpans":[],"textDirection":1,"textTextureScale":0}],"project_files":[".images\/1616411984664.imagitorImage"],"project_description":"حسنِ ازل ہے پیدا تاروں کی دلبری میں\nجس طرح عکسِ گُل ہو شبنم کی آرسی میں\nآئینِ نو سے ڈرنا، طرزِ کُہن پہ اَڑنا\nمنزل یہی کٹھن ہے قوموں کی زندگی میںاقبـالIMAGITORاردو ڈیزائن ایپ"}