{"viewId":1603962814920,"height":2000,"width":1600,"bgOverlayGradient":{"angle":90,"colors":["#70D0FEDB","#708BDDFF","#70B9D1FF"],"type":0,"grWidth":0,"grHeight":0},"backgroundOverlayColor":"#00000000","backgroundColor":"#FFFFFFFF","version":6,"subViews":[{"viewId":1603969779742,"layerFullLocked":true,"layerHidden":false,"layerLocked":"false","maskRoundRectRadius":0,"border":"30","borderColor":"#FFFFFFFF","opacity":"1.0","rotateAngle":"90.0","backgroundColor":"#00000000","xPoint":"0.0","yPoint":"0.0","selected":"false","layoutParamsHeight":"-2","layoutParamsWidth":"-2","rootLayoutHeight":"2240","rootLayoutWidth":"1635","textPadding":0,"viewType":"textView","zoomScale":"0.9000001","text":" ","textAlignment":"textCenterAlignment","textVerticalAlignment":"textTopAlignment","typeFaceName":"Mehr Nastaliq Web","typeFaceType":"urdu","textSize":"18","textSizeSP":63,"textColor":"#FFFF0000","flipHorizontal":"1.0","flipVertical":"1.0","stroke":"0.0","strokeColor":"#FF696969","shadowRadius":"0.0","shadowColor":"#FF444444","shadowX":"5.0","shadowY":"5.0","lineSpacing":"1.0","wordSpacing":0.0010000000474974513,"wordArc":0,"textBold":false,"textItalic":false,"textUnderline":false,"textEmboss":false,"textTextureScale":0},{"viewId":1603969946366,"layerFullLocked":true,"layerHidden":false,"layerLocked":"false","maskRoundRectRadius":30,"border":"0","borderColor":"#00000000","opacity":"0.1","rotateAngle":"90.0","backgroundColor":"#00000000","xPoint":"-31.111107","yPoint":"-27.777775","selected":"false","layoutParamsHeight":"-2","layoutParamsWidth":"-2","rootLayoutHeight":"422","rootLayoutWidth":"435","textPadding":0,"viewType":"textView","zoomScale":"0.9000001","text":"ﷺ","textAlignment":"textCenterAlignment","textVerticalAlignment":"textTopAlignment","typeFaceName":"Mehr Nastaliq Web","typeFaceType":"urdu","textSize":"56","textSizeSP":196,"textColor":"#FF2ECC40","flipHorizontal":"1.0","flipVertical":"1.0","stroke":"0.0","strokeColor":"#FF696969","shadowRadius":"69.0","shadowColor":"#FFFFFFFF","shadowX":"5.0","shadowY":"5.0","lineSpacing":"1.0","wordSpacing":0.0010000000474974513,"wordArc":0,"textBold":false,"textItalic":false,"textUnderline":false,"textEmboss":false,"textTextureScale":0},{"viewId":1603970013631,"layerFullLocked":true,"layerHidden":false,"layerLocked":"false","maskRoundRectRadius":30,"border":"0","borderColor":"#00000000","opacity":"0.1","rotateAngle":"90.0","backgroundColor":"#00000000","xPoint":"489.99994","yPoint":"428.88885","selected":"false","layoutParamsHeight":"-2","layoutParamsWidth":"-2","rootLayoutHeight":"422","rootLayoutWidth":"435","textPadding":0,"viewType":"textView","zoomScale":"0.9000001","text":"ﷺ","textAlignment":"textCenterAlignment","textVerticalAlignment":"textTopAlignment","typeFaceName":"Mehr Nastaliq Web","typeFaceType":"urdu","textSize":"56","textSizeSP":196,"textColor":"#FF2ECC40","flipHorizontal":"1.0","flipVertical":"1.0","stroke":"0.0","strokeColor":"#FF696969","shadowRadius":"69.0","shadowColor":"#FFFFFFFF","shadowX":"5.0","shadowY":"5.0","lineSpacing":"1.0","wordSpacing":0.0010000000474974513,"wordArc":0,"textBold":false,"textItalic":false,"textUnderline":false,"textEmboss":false,"textTextureScale":0},{"viewId":1603970033791,"layerFullLocked":true,"layerHidden":false,"layerLocked":"false","maskRoundRectRadius":0,"border":"0","borderColor":"#00000000","opacity":"1.0","rotateAngle":"90.0","backgroundColor":"#00000000","xPoint":"-31.111107","yPoint":"-27.777775","selected":"false","layoutParamsHeight":"-2","layoutParamsWidth":"-2","rootLayoutHeight":"878","rootLayoutWidth":"956","textPadding":0,"viewType":"groupView","groupChildIds":[{"viewId":1603969946366,"groupChildProps":{"xPoint":-31,"yPoint":-27,"width":435,"height":422,"border":0,"maskRoundRectRadius":30,"textSize":57,"stroke":0,"shadowRadius":69}},{"viewId":1603970013631,"groupChildProps":{"xPoint":489,"yPoint":428,"width":435,"height":422,"border":0,"maskRoundRectRadius":30,"textSize":56,"stroke":0,"shadowRadius":69}},{"viewId":1603970033791,"groupChildProps":{"xPoint":-31,"yPoint":-27,"width":956,"height":878,"border":0,"maskRoundRectRadius":0}}]},{"viewId":1603964243752,"layerFullLocked":true,"layerHidden":false,"layerLocked":"false","maskRoundRectRadius":0,"border":"0","borderColor":"#FF000000","opacity":"1.0","rotateAngle":"90.0","backgroundColor":"#00000000","xPoint":"-56.66666","yPoint":"141.1111","selected":"false","layoutParamsHeight":"-2","layoutParamsWidth":"-2","rootLayoutHeight":"573","rootLayoutWidth":"714","textPadding":0,"bitmapFilePath":".images\/1603964243752.imagitorImage","viewType":"imageView","zoomScale":"0.9000001","scaleType":"FIT_XY","flipHorizontal":1,"flipVertical":1,"tintColor":"#00000000","maskMode":0,"shadow":{"shadowRadius":32,"shadowColor":"#FFFFFFFF","shadowDist":15,"shadowAngle":45}},{"viewId":1603963422549,"layerFullLocked":false,"layerHidden":false,"layerLocked":"false","maskRoundRectRadius":0,"border":"0","borderColor":"#00000000","opacity":"1.0","rotateAngle":"90.0","backgroundColor":"#00000000","xPoint":"0.0","yPoint":"0.0","selected":"false","layoutParamsHeight":"-1","layoutParamsWidth":"-1","rootLayoutHeight":"2000","rootLayoutWidth":"1600","textPadding":0,"viewType":"shapeView2","zoomScale":"0.9000001","shapeLayers":[{"shapeType":"shapeSVG","shapeVertices":[{"xPoint":541.111083984375,"yPoint":447.354736328125},{"xPoint":541.111083984375,"yPoint":297.354736328125},{"xPoint":563.5546264648438,"yPoint":108.3970947265625},{"xPoint":769.801513671875,"yPoint":106.354736328125},{"xPoint":801.111083984375,"yPoint":288.354736328125},{"xPoint":801.111083984375,"yPoint":447.354736328125}],"shapeBezier":[{"xPoint":541.111083984375,"yPoint":384.69244384765625},{"xPoint":541.111083984375,"yPoint":341.01702880859375},{"xPoint":540.5449829101562,"yPoint":253.18475341796875},{"xPoint":528.950439453125,"yPoint":149.3170166015625},{"xPoint":619.8531494140625,"yPoint":53.66752624511719},{"xPoint":711.37353515625,"yPoint":48.01466369628906},{"xPoint":807.2020874023438,"yPoint":144.974365234375},{"xPoint":799.470947265625,"yPoint":234.53851318359375},{"xPoint":801.111083984375,"yPoint":335.0167236328125},{"xPoint":801.111083984375,"yPoint":381.6927490234375},{"xPoint":714.4530639648438,"yPoint":428.354736328125},{"xPoint":629.435546875,"yPoint":428.354736328125}],"fillColor":"#FF003D04","borderColor":"#FFA6D134","border":14,"joinType":1,"rotateAngle":45,"cornerRadius":0,"gradient":{"angle":90,"colors":["#FF003D04","#FF00A90A"],"type":0,"grWidth":0,"grHeight":0},"shadow":{"shadowRadius":0,"shadowColor":"#FF444444","shadowDist":15,"shadowAngle":45}}],"flipHorizontal":1,"flipVertical":1},{"viewId":1603963849407,"layerFullLocked":false,"layerHidden":false,"layerLocked":"false","maskRoundRectRadius":30,"border":"0","borderColor":"#00000000","opacity":"1.0","rotateAngle":"90.0","backgroundColor":"#00000000","xPoint":"569.6694","yPoint":"67.77777","selected":"false","layoutParamsHeight":"-2","layoutParamsWidth":"-2","rootLayoutHeight":"185","rootLayoutWidth":"196","textPadding":0,"viewType":"textView","zoomScale":"0.9000001","text":"1:40\nتا\n2:20","textAlignment":"textCenterAlignment","textVerticalAlignment":"textTopAlignment","typeFaceName":"arial","typeFaceType":"all","textSize":"18","textSizeSP":63,"textColor":"#FFFFFFFF","flipHorizontal":"1.0","flipVertical":"1.0","stroke":"0.0","strokeColor":"#FF696969","shadowRadius":"0.0","shadowColor":"#FF444444","shadowX":"5.0","shadowY":"5.0","lineSpacing":"0.8","wordSpacing":0.0010000000474974513,"wordArc":0,"textBold":true,"textItalic":false,"textUnderline":false,"textEmboss":false,"textTextureScale":0},{"viewId":1603964008242,"layerFullLocked":false,"layerHidden":false,"layerLocked":"false","maskRoundRectRadius":30,"border":"0","borderColor":"#00000000","opacity":"1.0","rotateAngle":"90.0","backgroundColor":"#00000000","xPoint":"575.11646","yPoint":"244.80804","selected":"false","layoutParamsHeight":"-2","layoutParamsWidth":"-2","rootLayoutHeight":"84","rootLayoutWidth":"196","textPadding":0,"viewType":"textView","zoomScale":"0.9000001","text":"مرکز مصطفے","textAlignment":"textCenterAlignment","textVerticalAlignment":"textTopAlignment","typeFaceName":"Mehr Nastaliq Web","typeFaceType":"urdu","textSize":"14","textSizeSP":49,"textColor":"#FFFFFFFF","flipHorizontal":"1.0","flipVertical":"1.0","stroke":"0.0","strokeColor":"#FF696969","shadowRadius":"0.0","shadowColor":"#FF444444","shadowX":"5.0","shadowY":"5.0","lineSpacing":"0.7","wordSpacing":0.0010000000474974513,"wordArc":0,"textBold":false,"textItalic":false,"textUnderline":false,"textEmboss":false,"textTextureScale":0},{"viewId":1603964049214,"layerFullLocked":false,"layerHidden":false,"layerLocked":"false","maskRoundRectRadius":30,"border":"0","borderColor":"#00000000","opacity":"1.0","rotateAngle":"90.0","backgroundColor":"#00000000","xPoint":"543.99023","yPoint":"326.5143","selected":"false","layoutParamsHeight":"-2","layoutParamsWidth":"-2","rootLayoutHeight":"126","rootLayoutWidth":"256","textPadding":0,"viewType":"textView","zoomScale":"0.9000001","text":"بالمقابل ایجوکیشن بورڈ گوجرانوالہ","textAlignment":"textCenterAlignment","textVerticalAlignment":"textTopAlignment","typeFaceName":"Mehr Nastaliq Web","typeFaceType":"urdu","textSize":"10","textSizeSP":35,"textColor":"#FFFFFFFF","flipHorizontal":"1.0","flipVertical":"1.0","stroke":"0.0","strokeColor":"#FF696969","shadowRadius":"0.0","shadowColor":"#FF444444","shadowX":"5.0","shadowY":"5.0","lineSpacing":"0.90000004","wordSpacing":0.0010000000474974513,"wordArc":0,"textBold":false,"textItalic":false,"textUnderline":false,"textEmboss":false,"textTextureScale":0},{"viewId":1603964215529,"layerFullLocked":false,"layerHidden":false,"layerLocked":"false","maskRoundRectRadius":0,"border":"0","borderColor":"#00000000","opacity":"1.0","rotateAngle":"90.0","backgroundColor":"#00000000","xPoint":"541.1111","yPoint":"67.77777","selected":"false","layoutParamsHeight":"-2","layoutParamsWidth":"-2","rootLayoutHeight":"384","rootLayoutWidth":"260","textPadding":0,"viewType":"groupView","groupChildIds":[{"viewId":1603963422549,"groupChildProps":{"xPoint":550,"yPoint":109,"width":260,"height":341,"border":7,"maskRoundRectRadius":0,"shadowRadius":0,"cornerRadius":0}},{"viewId":1603963849407,"groupChildProps":{"xPoint":578,"yPoint":70,"width":196,"height":181,"border":0,"maskRoundRectRadius":30,"textSize":19,"stroke":0,"shadowRadius":0}},{"viewId":1603964008242,"groupChildProps":{"xPoint":584,"yPoint":247,"width":196,"height":84,"border":0,"maskRoundRectRadius":30,"textSize":15,"stroke":0,"shadowRadius":0}},{"viewId":1603964049214,"groupChildProps":{"xPoint":552,"yPoint":329,"width":256,"height":126,"border":0,"maskRoundRectRadius":30,"textSize":11,"stroke":0,"shadowRadius":0}},{"viewId":1603964215529,"groupChildProps":{"xPoint":550,"yPoint":70,"width":260,"height":384,"border":0,"maskRoundRectRadius":0}}]},{"viewId":1603962911063,"layerFullLocked":true,"layerHidden":false,"layerLocked":"false","maskRoundRectRadius":30,"border":"0","borderColor":"#00000000","opacity":"1.0","rotateAngle":"90.0","backgroundColor":"#00000000","xPoint":"797.7778","yPoint":"20.0","selected":"false","layoutParamsHeight":"-2","layoutParamsWidth":"-2","rootLayoutHeight":"551","rootLayoutWidth":"774","textPadding":0,"viewType":"textView","zoomScale":"0.9000001","text":"خطبۂ\nجمعۃ المبارک","textAlignment":"textCenterAlignment","textVerticalAlignment":"textTopAlignment","typeFaceName":"nafees-riqa-regular","typeFaceType":"urdu","textSize":"56","textSizeSP":196,"textColor":"#FF88026E","flipHorizontal":"1.0","flipVertical":"1.0","stroke":"25.0","strokeColor":"#FFF9F2F4","shadowRadius":"21.0","shadowColor":"#FFB1D34D","shadowX":"5.0","shadowY":"5.0","lineSpacing":"0.7","wordSpacing":0.0010000000474974513,"wordArc":0,"textBold":false,"textItalic":false,"textUnderline":false,"textEmboss":false,"textTextureScale":0},{"viewId":1603964368526,"layerFullLocked":false,"layerHidden":false,"layerLocked":"false","maskRoundRectRadius":30,"border":"0","borderColor":"#00000000","opacity":"1.0","rotateAngle":"90.0","backgroundColor":"#00000000","xPoint":"27.760109","yPoint":"574.8656","selected":"false","layoutParamsHeight":"-2","layoutParamsWidth":"-2","rootLayoutHeight":"284","rootLayoutWidth":"598","textPadding":0,"viewType":"textView","zoomScale":"0.9000001","text":"مَرکَز مُصطفے","textAlignment":"textCenterAlignment","textVerticalAlignment":"textTopAlignment","typeFaceName":"gandhara-suls-regular","typeFaceType":"urdu","textSize":"36","textSizeSP":126,"textColor":"#FF87007B","flipHorizontal":"1.0","flipVertical":"1.0","stroke":"15.0","strokeColor":"#FFFFFFFF","shadowRadius":"7.0","shadowColor":"#FF28ACDD","shadowX":"3.0","shadowY":"0.0","lineSpacing":"1.0","wordSpacing":0.0010000000474974513,"wordArc":0,"textBold":false,"textItalic":false,"textUnderline":false,"textEmboss":false,"textTextureScale":0},{"viewId":1603965566033,"layerFullLocked":false,"layerHidden":false,"layerLocked":"false","maskRoundRectRadius":0,"border":"0","borderColor":"#00000000","opacity":"1.0","rotateAngle":"90.0","backgroundColor":"#00000000","xPoint":"0.0","yPoint":"0.0","selected":"false","layoutParamsHeight":"-1","layoutParamsWidth":"-1","rootLayoutHeight":"2000","rootLayoutWidth":"1600","textPadding":0,"viewType":"shapeView2","zoomScale":"0.9000001","shapeLayers":[{"shapeType":"shapePolygon","shapeVertices":[{"xPoint":235.47047424316406,"yPoint":1260.4283447265625},{"xPoint":415.9409484863281,"yPoint":1094.714111328125},{"xPoint":235.47035217285156,"yPoint":929},{"xPoint":55,"yPoint":1094.714111328125}],"shapeBezier":[{"xPoint":335.1412048339844,"yPoint":1260.4283447265625},{"xPoint":415.9409484863281,"yPoint":1186.235107421875},{"xPoint":415.9409484863281,"yPoint":1003.1928100585938},{"xPoint":335.1412048339844,"yPoint":929},{"xPoint":135.79934692382812,"yPoint":929},{"xPoint":55,"yPoint":1003.1928100585938},{"xPoint":55,"yPoint":1186.235107421875},{"xPoint":135.79934692382812,"yPoint":1260.4283447265625}],"fillColor":"#FF8D0173","borderColor":"#FF92D8F7","border":17,"joinType":1,"rotateAngle":0,"cornerRadius":0,"shadow":{"shadowRadius":0,"shadowColor":"#FF444444","shadowDist":15,"shadowAngle":45}}],"flipHorizontal":1,"flipVertical":1},{"viewId":1603965642530,"layerFullLocked":false,"layerHidden":false,"layerLocked":"false","maskRoundRectRadius":30,"border":"0","borderColor":"#00000000","opacity":"1.0","rotateAngle":"90.0","backgroundColor":"#00000000","xPoint":"68.13937","yPoint":"958.6831","selected":"false","layoutParamsHeight":"-2","layoutParamsWidth":"-2","rootLayoutHeight":"283","rootLayoutWidth":"335","textPadding":0,"viewType":"textView","zoomScale":"0.9000001","text":"شیرانوالہ باغ\nگوجرانوالہ","textAlignment":"textCenterAlignment","textVerticalAlignment":"textTopAlignment","typeFaceName":"Mehr Nastaliq Web","typeFaceType":"urdu","textSize":"24","textSizeSP":84,"textColor":"#FFFFFFFF","flipHorizontal":"1.0","flipVertical":"1.0","stroke":"0.0","strokeColor":"#FFFFFFFF","shadowRadius":"3.0","shadowColor":"#FF000000","shadowX":"3.0","shadowY":"4.0","lineSpacing":"0.8","wordSpacing":0.0010000000474974513,"wordArc":0,"textBold":false,"textItalic":false,"textUnderline":false,"textEmboss":false,"textTextureScale":0},{"viewId":1603965222370,"layerFullLocked":true,"layerHidden":false,"layerLocked":"false","maskRoundRectRadius":0,"border":"0","borderColor":"#00000000","opacity":"1.0","rotateAngle":"90.0","backgroundColor":"#00000000","xPoint":"0.0","yPoint":"0.0","selected":"false","layoutParamsHeight":"-1","layoutParamsWidth":"-1","rootLayoutHeight":"2000","rootLayoutWidth":"1600","textPadding":0,"viewType":"shapeView2","zoomScale":"0.9000001","shapeLayers":[{"shapeType":"shapePolygon","shapeVertices":[{"xPoint":233.77914428710938,"yPoint":981.083984375},{"xPoint":352,"yPoint":886},{"xPoint":300,"yPoint":886},{"xPoint":286.6412353515625,"yPoint":834},{"xPoint":180.91775512695312,"yPoint":834},{"xPoint":170,"yPoint":886},{"xPoint":115,"yPoint":886}],"shapeBezier":[{"xPoint":273.18212890625,"yPoint":949.3924560546875},{"xPoint":312.59698486328125,"yPoint":917.6915283203125},{"xPoint":334.66839599609375,"yPoint":886},{"xPoint":317.33160400390625,"yPoint":886},{"xPoint":295.5475158691406,"yPoint":868.66845703125},{"xPoint":291.0937194824219,"yPoint":851.3316650390625},{"xPoint":251.40359497070312,"yPoint":834},{"xPoint":216.1553955078125,"yPoint":834},{"xPoint":177.27886962890625,"yPoint":851.3316650390625},{"xPoint":173.63888549804688,"yPoint":868.66845703125},{"xPoint":151.6685028076172,"yPoint":886},{"xPoint":133.3314971923828,"yPoint":886},{"xPoint":154.58908081054688,"yPoint":917.6915283203125},{"xPoint":194.19004821777344,"yPoint":949.3924560546875}],"fillColor":"#FFC7EDF7","borderColor":"#FF28ACDD","border":8,"joinType":1,"rotateAngle":0,"cornerRadius":0,"shadow":{"shadowRadius":0,"shadowColor":"#FF444444","shadowDist":15,"shadowAngle":45}}],"flipHorizontal":1,"flipVertical":1},{"viewId":1603965150261,"layerFullLocked":true,"layerHidden":false,"layerLocked":"false","maskRoundRectRadius":30,"border":"0","borderColor":"#00000000","opacity":"1.0","rotateAngle":"90.0","backgroundColor":"#00000000","xPoint":"163.52557","yPoint":"768.1231","selected":"false","layoutParamsHeight":"-2","layoutParamsWidth":"-2","rootLayoutHeight":"190","rootLayoutWidth":"137","textPadding":0,"viewType":"textView","zoomScale":"0.9000001","text":"تا","textAlignment":"textCenterAlignment","textVerticalAlignment":"textTopAlignment","typeFaceName":"Mehr Nastaliq Web","typeFaceType":"urdu","textSize":"36","textSizeSP":126,"textColor":"#FF2D2F92","flipHorizontal":"1.0","flipVertical":"1.0","stroke":"0.0","strokeColor":"#FFFFFFFF","shadowRadius":"0.0","shadowColor":"#FF28ACDD","shadowX":"3.0","shadowY":"0.0","lineSpacing":"1.0","wordSpacing":0.0010000000474974513,"wordArc":0,"textBold":false,"textItalic":false,"textUnderline":false,"textEmboss":false,"textTextureScale":0},{"viewId":1603965770014,"layerFullLocked":true,"layerHidden":false,"layerLocked":"false","maskRoundRectRadius":30,"border":"0","borderColor":"#00000000","opacity":"1.0","rotateAngle":"90.0","backgroundColor":"#00000000","xPoint":"287.77774","yPoint":"627.7777","selected":"false","layoutParamsHeight":"-2","layoutParamsWidth":"-2","rootLayoutHeight":"821","rootLayoutWidth":"1313","textPadding":0,"viewType":"textView","zoomScale":"0.9000001","text":"میلاد ریلی","textAlignment":"textCenterAlignment","textVerticalAlignment":"textTopAlignment","typeFaceName":"alqalam-hassan-regular","typeFaceType":"urdu","textSize":"140","textSizeSP":490,"textColor":"#FFFF0000","flipHorizontal":"1.0","flipVertical":"1.0","stroke":"32.0","strokeColor":"#FF0D008B","shadowRadius":"4.0","shadowColor":"#FF28ACDD","shadowX":"1.0","shadowY":"5.0","lineSpacing":"0.7","wordSpacing":0.0010000000474974513,"wordArc":0,"textBold":false,"textItalic":false,"textUnderline":false,"textEmboss":false,"gradient":{"angle":90,"colors":["#FCFF1C","#FCFF1C","#FCFF1C","#E2C213","#E2C213"],"type":0,"grWidth":300,"grHeight":300},"textTextureScale":0},{"viewId":1603966046032,"layerFullLocked":true,"layerHidden":false,"layerLocked":"false","maskRoundRectRadius":0,"border":"0","borderColor":"#00000000","opacity":"1.0","rotateAngle":"90.0","backgroundColor":"#00000000","xPoint":"0.0","yPoint":"0.0","selected":"false","layoutParamsHeight":"-1","layoutParamsWidth":"-1","rootLayoutHeight":"2000","rootLayoutWidth":"1600","textPadding":0,"viewType":"shapeView2","zoomScale":"0.9000001","shapeLayers":[{"shapeType":"shapeSVG","shapeVertices":[{"xPoint":1204.980712890625,"yPoint":953.5194702148438},{"xPoint":1380.91162109375,"yPoint":991.1007690429688},{"xPoint":1395.6123046875,"yPoint":983.2706298828125},{"xPoint":1369.166748046875,"yPoint":930.6078491210938},{"xPoint":1556.8831787109375,"yPoint":849.2827758789062},{"xPoint":1561.0174560546875,"yPoint":835.2958984375},{"xPoint":1523.789306640625,"yPoint":761.1624755859375},{"xPoint":1511.880859375,"yPoint":756},{"xPoint":1326.49072265625,"yPoint":836.3167724609375},{"xPoint":1302.0675048828125,"yPoint":787.6821899414062},{"xPoint":1283.7210693359375,"yPoint":790.0077514648438},{"xPoint":1196,"yPoint":938.2698974609375},{"xPoint":1204.9808349609375,"yPoint":953.5203247070312}],"shapeBezier":[{"xPoint":1322.2738037109375,"yPoint":978.5747680664062},{"xPoint":1263.617431640625,"yPoint":966.0453491210938},{"xPoint":1380.91162109375,"yPoint":991.1007690429688},{"xPoint":1403.3309326171875,"yPoint":998.640869140625},{"xPoint":1377.981201171875,"yPoint":948.1603393554688},{"xPoint":1386.7979736328125,"yPoint":965.7186279296875},{"xPoint":1494.31787109375,"yPoint":876.38818359375},{"xPoint":1431.7322998046875,"yPoint":903.50244140625},{"xPoint":1556.8831787109375,"yPoint":849.2827758789062},{"xPoint":1567.093505859375,"yPoint":847.3951416015625},{"xPoint":1536.19775390625,"yPoint":785.8710327148438},{"xPoint":1548.609130859375,"yPoint":810.5869140625},{"xPoint":1519.4415283203125,"yPoint":752.5037841796875},{"xPoint":1511.880859375,"yPoint":756},{"xPoint":1388.2808837890625,"yPoint":809.5474853515625},{"xPoint":1450.089599609375,"yPoint":782.7697143554688},{"xPoint":1310.20751953125,"yPoint":803.8922729492188},{"xPoint":1318.3504638671875,"yPoint":820.1065063476562},{"xPoint":1292.6669921875,"yPoint":768.9622802734375},{"xPoint":1283.7210693359375,"yPoint":790.0077514648438},{"xPoint":1283.7210693359375,"yPoint":790.0077514648438},{"xPoint":1203.1187744140625,"yPoint":921.73486328125},{"xPoint":1190.8935546875,"yPoint":950.3209838867188},{"xPoint":1204.9808349609375,"yPoint":953.5203247070312},{"xPoint":1204.9808349609375,"yPoint":953.5195922851562},{"xPoint":1204.9808349609375,"yPoint":953.5200805664062}],"fillColor":"#FF060299","borderColor":"#FF000000","border":0,"joinType":1,"rotateAngle":-25,"cornerRadius":0,"shadow":{"shadowRadius":0,"shadowColor":"#FF444444","shadowDist":15,"shadowAngle":45}}],"flipHorizontal":1,"flipVertical":1},{"viewId":1603966116472,"layerFullLocked":false,"layerHidden":false,"layerLocked":"false","maskRoundRectRadius":30,"border":"0","borderColor":"#00000000","opacity":"1.0","rotateAngle":"65.0","backgroundColor":"#00000000","xPoint":"1220.0001","yPoint":"801.1112","selected":"false","layoutParamsHeight":"-2","layoutParamsWidth":"-2","rootLayoutHeight":"176","rootLayoutWidth":"376","textPadding":0,"viewType":"textView","zoomScale":"0.9000001","text":"بعد نماز جمعۃالمبارک","textAlignment":"textCenterAlignment","textVerticalAlignment":"textTopAlignment","typeFaceName":"Mehr Nastaliq Web","typeFaceType":"urdu","textSize":"16","textSizeSP":56,"textColor":"#FFF9FD2A","flipHorizontal":"1.0","flipVertical":"1.0","stroke":"0.0","strokeColor":"#FFFFFFFF","shadowRadius":"3.0","shadowColor":"#FF000000","shadowX":"3.0","shadowY":"4.0","lineSpacing":"0.8","wordSpacing":0.0010000000474974513,"wordArc":0,"textBold":false,"textItalic":false,"textUnderline":false,"textEmboss":false,"textTextureScale":0},{"viewId":1603966229023,"layerFullLocked":true,"layerHidden":false,"layerLocked":"false","maskRoundRectRadius":0,"border":"0","borderColor":"#00000000","opacity":"1.0","rotateAngle":"90.0","backgroundColor":"#00000000","xPoint":"0.0","yPoint":"0.0","selected":"false","layoutParamsHeight":"-1","layoutParamsWidth":"-1","rootLayoutHeight":"2000","rootLayoutWidth":"1600","textPadding":0,"viewType":"shapeView2","zoomScale":"0.9000001","shapeLayers":[{"shapeType":"shapePolygon","shapeVertices":[{"xPoint":893,"yPoint":725.6284790039062},{"xPoint":1547.109619140625,"yPoint":725.6284790039062},{"xPoint":1547.109619140625,"yPoint":587},{"xPoint":893,"yPoint":587}],"shapeBezier":[{"xPoint":1111.0146484375,"yPoint":725.6284790039062},{"xPoint":1329.0946044921875,"yPoint":725.6284790039062},{"xPoint":1547.109619140625,"yPoint":679.4234008789062},{"xPoint":1547.109619140625,"yPoint":633.2050170898438},{"xPoint":1329.0946044921875,"yPoint":587},{"xPoint":1111.0146484375,"yPoint":587},{"xPoint":893,"yPoint":633.2050170898438},{"xPoint":893,"yPoint":679.4234008789062}],"fillColor":"#FF31701F","borderColor":"#FFFFE400","border":8,"joinType":1,"rotateAngle":0,"cornerRadius":17,"gradient":{"angle":90,"colors":["#FF31701F","#FF103700","#FF2D681C"],"type":0,"grWidth":0,"grHeight":0},"shadow":{"shadowRadius":7,"shadowColor":"#FF55C235","shadowDist":15,"shadowAngle":45}}],"flipHorizontal":1,"flipVertical":1},{"viewId":1603966349374,"layerFullLocked":false,"layerHidden":false,"layerLocked":"false","maskRoundRectRadius":30,"border":"0","borderColor":"#00000000","opacity":"1.0","rotateAngle":"90.0","backgroundColor":"#00000000","xPoint":"925.5555","yPoint":"565.5555","selected":"false","layoutParamsHeight":"-2","layoutParamsWidth":"-2","rootLayoutHeight":"176","rootLayoutWidth":"578","textPadding":0,"viewType":"textView","zoomScale":"0.9000001","text":"12ربیع الاول1442","textAlignment":"textCenterAlignment","textVerticalAlignment":"textTopAlignment","typeFaceName":"Mehr Nastaliq Web","typeFaceType":"urdu","textSize":"24","textSizeSP":84,"textColor":"#FFFFFFFF","flipHorizontal":"1.0","flipVertical":"1.0","stroke":"0.0","strokeColor":"#FFFFFFFF","shadowRadius":"3.0","shadowColor":"#FF000000","shadowX":"3.0","shadowY":"4.0","lineSpacing":"0.8","wordSpacing":0.0010000000474974513,"wordArc":0,"textBold":false,"textItalic":false,"textUnderline":false,"textEmboss":false,"textTextureScale":0},{"viewId":1603966462426,"layerFullLocked":false,"layerHidden":false,"layerLocked":"false","maskRoundRectRadius":30,"border":"0","borderColor":"#00000000","opacity":"1.0","rotateAngle":"90.0","backgroundColor":"#00000000","xPoint":"619.99994","yPoint":"749.99994","selected":"false","layoutParamsHeight":"-2","layoutParamsWidth":"-2","rootLayoutHeight":"267","rootLayoutWidth":"560","textPadding":0,"viewType":"textView","zoomScale":"0.9000001","text":"درود و سلام پڑھتی سرمدی ساعتوں کے جھرمٹ میں","textAlignment":"textCenterAlignment","textVerticalAlignment":"textTopAlignment","typeFaceName":"Mehr Nastaliq Web","typeFaceType":"urdu","textSize":"22","textSizeSP":77,"textColor":"#FFFF0000","flipHorizontal":"1.0","flipVertical":"1.0","stroke":"6.0","strokeColor":"#FF000000","shadowRadius":"1.9","shadowColor":"#FF170E0B","shadowX":"2.0","shadowY":"5.0","lineSpacing":"0.8","wordSpacing":0.0010000000474974513,"wordArc":0,"textBold":false,"textItalic":false,"textUnderline":false,"textEmboss":false,"gradient":{"angle":90,"colors":["#FFFC00","#00F4FF"],"type":0,"grWidth":0,"grHeight":0},"textTextureScale":0},{"viewId":1603968202304,"layerFullLocked":true,"layerHidden":false,"layerLocked":"true","maskRoundRectRadius":0,"border":"0","borderColor":"#FF000000","opacity":"1.0","rotateAngle":"90.0","backgroundColor":"#00000000","xPoint":"442.22223","yPoint":"1357.7778","selected":"false","layoutParamsHeight":"-2","layoutParamsWidth":"-2","rootLayoutHeight":"471","rootLayoutWidth":"1103","textPadding":0,"bitmapFilePath":".images\/1603968202304.imagitorImage","viewType":"imageView","zoomScale":"0.9000001","scaleType":"FIT_XY","flipHorizontal":1,"flipVertical":1,"tintColor":"#00000000","maskMode":0,"shadow":{"shadowRadius":0,"shadowColor":"#FF444444","shadowDist":15,"shadowAngle":45}},{"viewId":1603968317862,"layerFullLocked":false,"layerHidden":false,"layerLocked":"false","maskRoundRectRadius":30,"border":"0","borderColor":"#00000000","opacity":"1.0","rotateAngle":"90.0","backgroundColor":"#00000000","xPoint":"491.20508","yPoint":"1451.2877","selected":"false","layoutParamsHeight":"-2","layoutParamsWidth":"-2","rootLayoutHeight":"234","rootLayoutWidth":"867","textPadding":0,"viewType":"textView","zoomScale":"0.9000001","text":"محمد رضا ثاقب مصطفائی","textAlignment":"textCenterAlignment","textVerticalAlignment":"textTopAlignment","typeFaceName":"nafees-riqa-regular","typeFaceType":"urdu","textSize":"36","textSizeSP":126,"textColor":"#FFFF0000","flipHorizontal":"1.0","flipVertical":"1.0","stroke":"5.0","strokeColor":"#FF000000","shadowRadius":"1.7","shadowColor":"#FF170E0B","shadowX":"2.0","shadowY":"5.0","lineSpacing":"0.8","wordSpacing":0.0010000000474974513,"wordArc":0,"textBold":false,"textItalic":false,"textUnderline":false,"textEmboss":false,"gradient":{"angle":90,"colors":["#FFFFFC00","#FFFF0000"],"type":0,"grWidth":0,"grHeight":0},"textTextureScale":0},{"viewId":1603968384125,"layerFullLocked":false,"layerHidden":false,"layerLocked":"false","maskRoundRectRadius":30,"border":"0","borderColor":"#00000000","opacity":"1.0","rotateAngle":"90.0","backgroundColor":"#00000000","xPoint":"1343.9717","yPoint":"1468.5735","selected":"false","layoutParamsHeight":"-2","layoutParamsWidth":"-2","rootLayoutHeight":"189","rootLayoutWidth":"153","textPadding":0,"viewType":"textView","zoomScale":"0.9000001","text":"عالمی مبلغ\nپیرزادہ","textAlignment":"textLeftAlignment","textVerticalAlignment":"textTopAlignment","typeFaceName":"Mehr Nastaliq Web","typeFaceType":"urdu","textSize":"16","textSizeSP":56,"textColor":"#FFFFFFFF","flipHorizontal":"1.0","flipVertical":"1.0","stroke":"0.0","strokeColor":"#FFFFFFFF","shadowRadius":"3.0","shadowColor":"#FF000000","shadowX":"3.0","shadowY":"4.0","lineSpacing":"0.8","wordSpacing":0.0010000000474974513,"wordArc":0,"textBold":false,"textItalic":false,"textUnderline":false,"textEmboss":false,"textTextureScale":0},{"viewId":1603968485481,"layerFullLocked":false,"layerHidden":false,"layerLocked":"false","maskRoundRectRadius":30,"border":"0","borderColor":"#00000000","opacity":"1.0","rotateAngle":"90.0","backgroundColor":"#00000000","xPoint":"765.6173","yPoint":"1400.1505","selected":"false","layoutParamsHeight":"-2","layoutParamsWidth":"-2","rootLayoutHeight":"120","rootLayoutWidth":"457","textPadding":0,"viewType":"textView","zoomScale":"0.9000001","text":"قیادت و خطابت","textAlignment":"textCenterAlignment","textVerticalAlignment":"textTopAlignment","typeFaceName":"alqalam-telenor-regular","typeFaceType":"urdu","textSize":"18","textSizeSP":63,"textColor":"#FFFF0000","flipHorizontal":"1.0","flipVertical":"1.0","stroke":"7.0","strokeColor":"#FFFFFFFF","shadowRadius":"0.0","shadowColor":"#FF000000","shadowX":"3.0","shadowY":"4.0","lineSpacing":"0.8","wordSpacing":0.0010000000474974513,"wordArc":0,"textBold":false,"textItalic":false,"textUnderline":false,"textEmboss":false,"textTextureScale":0},{"viewId":1603968562498,"layerFullLocked":false,"layerHidden":false,"layerLocked":"false","maskRoundRectRadius":30,"border":"0","borderColor":"#00000000","opacity":"1.0","rotateAngle":"90.0","backgroundColor":"#00000000","xPoint":"754.81366","yPoint":"1633.5089","selected":"false","layoutParamsHeight":"-2","layoutParamsWidth":"-2","rootLayoutHeight":"105","rootLayoutWidth":"476","textPadding":0,"viewType":"textView","zoomScale":"0.9000001","text":"امیر اعلی ادارہ مصطفے انٹرنیشنل","textAlignment":"textCenterAlignment","textVerticalAlignment":"textTopAlignment","typeFaceName":"Mehr Nastaliq Web","typeFaceType":"urdu","textSize":"16","textSizeSP":56,"textColor":"#FFFFFFFF","flipHorizontal":"1.0","flipVertical":"1.0","stroke":"0.0","strokeColor":"#FFFFFFFF","shadowRadius":"3.0","shadowColor":"#FF000000","shadowX":"3.0","shadowY":"4.0","lineSpacing":"0.8","wordSpacing":0.0010000000474974513,"wordArc":0,"textBold":false,"textItalic":false,"textUnderline":false,"textEmboss":false,"textTextureScale":0},{"viewId":1603968818618,"layerFullLocked":true,"layerHidden":false,"layerLocked":"false","maskRoundRectRadius":0,"border":"0","borderColor":"#00000000","opacity":"0.5","rotateAngle":"90.0","backgroundColor":"#00000000","xPoint":"0.0","yPoint":"0.0","selected":"false","layoutParamsHeight":"-1","layoutParamsWidth":"-1","rootLayoutHeight":"2000","rootLayoutWidth":"1600","textPadding":0,"viewType":"shapeView2","zoomScale":"0.9000001","shapeLayers":[{"shapeType":"shapeSVG","shapeVertices":[{"xPoint":107.9129638671875,"yPoint":1801.777587890625},{"xPoint":103.47201538085938,"yPoint":1795.968994140625},{"xPoint":65.53309631347656,"yPoint":1746.347900390625},{"xPoint":61.11110305786133,"yPoint":1740.5394287109375},{"xPoint":61.11110305786133,"yPoint":1408.00341796875},{"xPoint":65.53309631347656,"yPoint":1402.20947265625},{"xPoint":103.47201538085938,"yPoint":1352.572265625},{"xPoint":107.9129638671875,"yPoint":1346.777587890625},{"xPoint":362.1791076660156,"yPoint":1346.777587890625},{"xPoint":366.6201171875,"yPoint":1352.572265625},{"xPoint":404.5609436035156,"yPoint":1402.20947265625},{"xPoint":408.9999694824219,"yPoint":1408.00341796875},{"xPoint":408.9999694824219,"yPoint":1740.51416015625},{"xPoint":404.5609436035156,"yPoint":1746.3226318359375},{"xPoint":366.6201171875,"yPoint":1795.943603515625},{"xPoint":362.1791076660156,"yPoint":1801.752197265625},{"xPoint":107.9129638671875,"yPoint":1801.752197265625}],"shapeBezier":[{"xPoint":105.47135925292969,"yPoint":1801.777587890625},{"xPoint":103.47201538085938,"yPoint":1799.1644287109375},{"xPoint":103.47201538085938,"yPoint":1768.6083984375},{"xPoint":86.45262145996094,"yPoint":1746.347900390625},{"xPoint":63.08977127075195,"yPoint":1746.347900390625},{"xPoint":61.11110305786133,"yPoint":1743.7333984375},{"xPoint":61.11110305786133,"yPoint":1518.83740234375},{"xPoint":61.11110305786133,"yPoint":1629.705078125},{"xPoint":61.11110305786133,"yPoint":1404.8057861328125},{"xPoint":63.08977127075195,"yPoint":1402.20947265625},{"xPoint":86.45262145996094,"yPoint":1402.20947265625},{"xPoint":103.47201538085938,"yPoint":1379.9442138671875},{"xPoint":103.47201538085938,"yPoint":1349.376953125},{"xPoint":105.47114562988281,"yPoint":1346.777587890625},{"xPoint":277.4322814941406,"yPoint":1346.777587890625},{"xPoint":192.65992736816406,"yPoint":1346.777587890625},{"xPoint":364.6242370605469,"yPoint":1346.777587890625},{"xPoint":366.6201171875,"yPoint":1349.376953125},{"xPoint":366.6201171875,"yPoint":1379.946044921875},{"xPoint":383.64105224609375,"yPoint":1402.20947265625},{"xPoint":407.00408935546875,"yPoint":1402.20947265625},{"xPoint":408.9999694824219,"yPoint":1404.8057861328125},{"xPoint":408.9999694824219,"yPoint":1629.688232421875},{"xPoint":408.9999694824219,"yPoint":1518.8291015625},{"xPoint":408.9999694824219,"yPoint":1743.707763671875},{"xPoint":407.00408935546875,"yPoint":1746.3226318359375},{"xPoint":383.6411437988281,"yPoint":1746.3226318359375},{"xPoint":366.6201171875,"yPoint":1768.5821533203125},{"xPoint":366.6201171875,"yPoint":1799.14013671875},{"xPoint":364.6242370605469,"yPoint":1801.752197265625},{"xPoint":192.65992736816406,"yPoint":1801.752197265625},{"xPoint":277.4322814941406,"yPoint":1801.752197265625},{"xPoint":107.9129638671875,"yPoint":1801.7685546875},{"xPoint":107.9129638671875,"yPoint":1801.760986328125}],"fillColor":"#FFD1F1AE","borderColor":"#FFA6D054","border":7,"joinType":1,"rotateAngle":0,"cornerRadius":0,"shadow":{"shadowRadius":0,"shadowColor":"#FF444444","shadowDist":15,"shadowAngle":45}}],"flipHorizontal":1,"flipVertical":1},{"viewId":1603968857803,"layerFullLocked":true,"layerHidden":false,"layerLocked":"false","maskRoundRectRadius":30,"border":"0","borderColor":"#00000000","opacity":"1.0","rotateAngle":"90.0","backgroundColor":"#00000000","xPoint":"88.1111","yPoint":"1337.7776","selected":"false","layoutParamsHeight":"-2","layoutParamsWidth":"-2","rootLayoutHeight":"464","rootLayoutWidth":"300","textPadding":11,"viewType":"textView","zoomScale":"0.9000001","text":"قافلہ در قافلہ شریک ہو کر اپنے آقا و مولا کے حضور اپنی محبتوں کا خراج پیش کیجئے","textAlignment":"textCenterAlignment","textVerticalAlignment":"textTopAlignment","typeFaceName":"Mehr Nastaliq Web","typeFaceType":"urdu","textSize":"18","textSizeSP":63,"textColor":"#FF6A945B","flipHorizontal":"1.0","flipVertical":"1.0","stroke":"6.0","strokeColor":"#FFE7F7D5","shadowRadius":"0.0","shadowColor":"#FF000000","shadowX":"3.0","shadowY":"4.0","lineSpacing":"0.7","wordSpacing":0.0010000000474974513,"wordArc":0,"textBold":false,"textItalic":false,"textUnderline":false,"textEmboss":false,"textTextureScale":0},{"viewId":1603969925371,"layerFullLocked":false,"layerHidden":false,"layerLocked":"false","maskRoundRectRadius":0,"border":"0","borderColor":"#00000000","opacity":"1.0","rotateAngle":"90.0","backgroundColor":"#00000000","xPoint":"61.111103","yPoint":"1337.7776","selected":"false","layoutParamsHeight":"-2","layoutParamsWidth":"-2","rootLayoutHeight":"464","rootLayoutWidth":"347","textPadding":0,"viewType":"groupView","groupChildIds":[{"viewId":1603968818618,"groupChildProps":{"xPoint":71,"yPoint":1415,"width":347,"height":455,"border":7,"maskRoundRectRadius":0,"shadowRadius":0,"cornerRadius":0}},{"viewId":1603968857803,"groupChildProps":{"xPoint":98,"yPoint":1406,"width":300,"height":464,"border":0,"maskRoundRectRadius":30,"textSize":18,"stroke":6,"shadowRadius":0}},{"viewId":1603969925371,"groupChildProps":{"xPoint":71,"yPoint":1406,"width":347,"height":464,"border":0,"maskRoundRectRadius":0}}]},{"viewId":1603969655625,"layerFullLocked":false,"layerHidden":false,"layerLocked":"false","maskRoundRectRadius":30,"border":"0","borderColor":"#00000000","opacity":"1.0","rotateAngle":"90.0","backgroundColor":"#00000000","xPoint":"53.4","yPoint":"1877.4","selected":"false","layoutParamsHeight":"-2","layoutParamsWidth":"-2","rootLayoutHeight":"94","rootLayoutWidth":"70","textPadding":0,"viewType":"shapeView","zoomScale":"0.9000001","text":"E","textAlignment":"textCenterAlignment","textVerticalAlignment":"textTopAlignment","typeFaceName":"social_media.otf","typeFaceType":"icon","textSize":"18","textSizeSP":63,"textColor":"#FF0074D9","flipHorizontal":"1.0","flipVertical":"1.0","stroke":"0.0","strokeColor":"#FF696969","shadowRadius":"0.0","shadowColor":"#FF444444","shadowX":"5.0","shadowY":"5.0","lineSpacing":"1.0","wordSpacing":0.0010000000474974513,"wordArc":0,"textBold":false,"textItalic":false,"textUnderline":false,"textEmboss":false,"textTextureScale":0,"shapeViewVer":2},{"viewId":1603969193477,"layerFullLocked":false,"layerHidden":false,"layerLocked":"false","maskRoundRectRadius":0,"border":"0","borderColor":"#00000000","opacity":"1.0","rotateAngle":"90.0","backgroundColor":"#00000000","xPoint":"0.0","yPoint":"0.0","selected":"false","layoutParamsHeight":"-1","layoutParamsWidth":"-1","rootLayoutHeight":"2000","rootLayoutWidth":"1600","textPadding":0,"viewType":"shapeView2","zoomScale":"0.9000001","shapeLayers":[{"shapeType":"shapeSVG","shapeVertices":[{"xPoint":1503.7777099609375,"yPoint":1950.63720703125},{"xPoint":534.6482543945312,"yPoint":1951.2581787109375},{"xPoint":477.7777404785156,"yPoint":1905.068359375},{"xPoint":477.7777404785156,"yPoint":1814.2581787109375},{"xPoint":1448.1512451171875,"yPoint":1814.2581787109375},{"xPoint":1503.7777099609375,"yPoint":1859.7178955078125},{"xPoint":1503.7777099609375,"yPoint":1950.63720703125}],"shapeBezier":[{"xPoint":1180.7669677734375,"yPoint":1950.84423828125},{"xPoint":604.6279907226562,"yPoint":1951.2581787109375},{"xPoint":478.9797668457031,"yPoint":1951.2581787109375},{"xPoint":477.7777404785156,"yPoint":1927.308349609375},{"xPoint":477.7777404785156,"yPoint":1883.9456787109375},{"xPoint":477.8031921386719,"yPoint":1844.6199951171875},{"xPoint":514.9525756835938,"yPoint":1814.2581787109375},{"xPoint":1124.7259521484375,"yPoint":1814.2581787109375},{"xPoint":1501.7064208984375,"yPoint":1814.012451171875},{"xPoint":1504.9207763671875,"yPoint":1819.1727294921875},{"xPoint":1502.4483642578125,"yPoint":1900.7545166015625},{"xPoint":1501.7064208984375,"yPoint":1920.9041748046875},{"xPoint":639.6126098632812,"yPoint":1951.2581787109375},{"xPoint":1503.7777099609375,"yPoint":1950.63720703125}],"fillColor":"#FF52C234","borderColor":"#FFE3CD7F","border":8,"joinType":1,"rotateAngle":0,"cornerRadius":0,"gradient":{"angle":90,"colors":["#FF52C234","#FF061700"],"type":0,"grWidth":0,"grHeight":0},"shadow":{"shadowRadius":0,"shadowColor":"#FF444444","shadowDist":15,"shadowAngle":45}}],"flipHorizontal":1,"flipVertical":1},{"viewId":1603969142199,"layerFullLocked":false,"layerHidden":false,"layerLocked":"false","maskRoundRectRadius":37,"border":"0","borderColor":"#00000000","opacity":"1.0","rotateAngle":"90.0","backgroundColor":"#00000000","xPoint":"994.0","yPoint":"1800.0","selected":"false","layoutParamsHeight":"-2","layoutParamsWidth":"-2","rootLayoutHeight":"152","rootLayoutWidth":"504","textPadding":0,"viewType":"textView","zoomScale":"0.9000001","text":"ادارہ مصطفے انٹرنیشنل","textAlignment":"textCenterAlignment","textVerticalAlignment":"textTopAlignment","typeFaceName":"Mehr Nastaliq Web","typeFaceType":"urdu","textSize":"22","textSizeSP":77,"textColor":"#FFFFFFFF","flipHorizontal":"1.0","flipVertical":"1.0","stroke":"0.0","strokeColor":"#FFE7F7D5","shadowRadius":"0.0","shadowColor":"#FF000000","shadowX":"3.0","shadowY":"4.0","lineSpacing":"0.7","wordSpacing":0.0010000000474974513,"wordArc":0,"textBold":false,"textItalic":false,"textUnderline":false,"textEmboss":false,"textTextureScale":0},{"viewId":1603969560888,"layerFullLocked":false,"layerHidden":false,"layerLocked":"false","maskRoundRectRadius":37,"border":"0","borderColor":"#00000000","opacity":"1.0","rotateAngle":"90.0","backgroundColor":"#00000000","xPoint":"505.12262","yPoint":"1826.9934","selected":"false","layoutParamsHeight":"-2","layoutParamsWidth":"-2","rootLayoutHeight":"103","rootLayoutWidth":"505","textPadding":11,"viewType":"textView","zoomScale":"0.9000001","text":"+92 55 385 1295","textAlignment":"textCenterAlignment","textVerticalAlignment":"textTopAlignment","typeFaceName":"arial","typeFaceType":"all","textSize":"17","textSizeSP":59,"textColor":"#FFFFFFFF","flipHorizontal":"1.0","flipVertical":"1.0","stroke":"0.0","strokeColor":"#FFE7F7D5","shadowRadius":"0.0","shadowColor":"#FF000000","shadowX":"3.0","shadowY":"4.0","lineSpacing":"0.7","wordSpacing":0.0010000000474974513,"wordArc":0,"textBold":false,"textItalic":false,"textUnderline":false,"textEmboss":false,"textTextureScale":0},{"viewId":1603969694184,"layerFullLocked":false,"layerHidden":false,"layerLocked":"false","maskRoundRectRadius":30,"border":"0","borderColor":"#00000000","opacity":"1.0","rotateAngle":"90.0","backgroundColor":"#00000000","xPoint":"130.6","yPoint":"1863.2","selected":"false","layoutParamsHeight":"-2","layoutParamsWidth":"-2","rootLayoutHeight":"94","rootLayoutWidth":"213","textPadding":0,"viewType":"textView","zoomScale":"0.9000001","text":"Muhammad Raza SaQib Mustafai","textAlignment":"textLeftAlignment","textVerticalAlignment":"textTopAlignment","typeFaceName":"Oswald-Regular","typeFaceType":"all","textSize":"9","textSizeSP":31,"textColor":"#FF111111","flipHorizontal":"1.0","flipVertical":"1.0","stroke":"0.0","strokeColor":"#FFE7F7D5","shadowRadius":"0.0","shadowColor":"#FF000000","shadowX":"3.0","shadowY":"4.0","lineSpacing":"0.7","wordSpacing":0.0010000000474974513,"wordArc":0,"textBold":false,"textItalic":false,"textUnderline":false,"textEmboss":false,"textTextureScale":0}],"project_files":[".images\/1603964243752.imagitorImage",".images\/1603968202304.imagitorImage"],"project_description":" ﷺﷺ1:40\nتا\n2:20مرکز مصطفےبالمقابل ایجوکیشن بورڈ گوجرانوالہخطبۂ\nجمعۃ المبارکمَرکَز مُصطفےشیرانوالہ باغ\nگوجرانوالہتامیلاد ریلیبعد نماز جمعۃالمبارک12ربیع الاول1442درود و سلام پڑھتی سرمدی ساعتوں کے جھرمٹ میںمحمد رضا ثاقب مصطفائیعالمی مبلغ\nپیرزادہقیادت و خطابتامیر اعلی ادارہ مصطفے انٹرنیشنلقافلہ در قافلہ شریک ہو کر اپنے آقا و مولا کے حضور اپنی محبتوں کا خراج پیش کیجئےEادارہ مصطفے انٹرنیشنل+92 55 385 1295Muhammad Raza SaQib Mustafai"}