{"viewId":1589055521972,"height":1125,"width":2000,"bgOverlayGradient":{"angle":0,"colors":["#FFEC008C","#FFFC6767"],"type":0,"grWidth":0,"grHeight":0},"backgroundOverlayColor":"#00000000","backgroundColor":"#FFFFFFFF","version":4,"subViews":[{"viewId":1589055539388,"layerFullLocked":false,"layerHidden":false,"layerLocked":"false","maskRoundRectRadius":0,"border":"0","borderColor":"#FF000000","opacity":"1.0","rotateAngle":"90.0","backgroundColor":"#00000000","xPoint":"1544.4443","yPoint":"259.25925","selected":"false","layoutParamsHeight":"-2","layoutParamsWidth":"-2","rootLayoutHeight":"775","rootLayoutWidth":"392","textPadding":0,"bitmapFilePath":".images\/1589055539388.imagitorImage","viewType":"imageView","zoomScale":"0.54","scaleType":"FIT_XY","flipHorizontal":1,"flipVertical":1,"maskMode":0},{"viewId":1589055576297,"layerFullLocked":false,"layerHidden":false,"layerLocked":"false","maskRoundRectRadius":0,"border":"0","borderColor":"#FF000000","opacity":"1.0","rotateAngle":"90.0","backgroundColor":"#00000000","xPoint":"1337.037","yPoint":"790.7407","selected":"false","layoutParamsHeight":"-2","layoutParamsWidth":"-2","rootLayoutHeight":"318","rootLayoutWidth":"372","textPadding":0,"bitmapFilePath":".images\/1589055576297.imagitorImage","viewType":"imageView","zoomScale":"0.54","scaleType":"FIT_CENTER","flipHorizontal":1,"flipVertical":1,"maskMode":0},{"viewId":1589055603691,"layerFullLocked":false,"layerHidden":false,"layerLocked":"false","maskRoundRectRadius":30,"border":"0","borderColor":"#00000000","opacity":"1.0","rotateAngle":"90.0","backgroundColor":"#00000000","xPoint":"72.22222","yPoint":"198.14815","selected":"false","layoutParamsHeight":"-2","layoutParamsWidth":"-2","rootLayoutHeight":"368","rootLayoutWidth":"1407","textPadding":0,"viewType":"textView","zoomScale":"0.54","text":"روزے کے روحانی ثمرات","textAlignment":"textCenterAlignment","textVerticalAlignment":"textTopAlignment","typeFaceName":"Mehr Nastaliq Web","typeFaceType":"urdu","textSize":"64","textSizeSP":192,"textColor":"#FFFF0000","flipHorizontal":"1.0","flipVertical":"1.0","stroke":"26.0","strokeColor":"#FF000000","shadowRadius":"1.9","shadowColor":"#FF170E0B","shadowX":"2.0","shadowY":"5.0","lineSpacing":"1.0","wordSpacing":0.0010000000474974513,"wordArc":0,"textBold":false,"textItalic":false,"textUnderline":false,"textEmboss":false,"gradient":{"angle":90,"colors":["#FF00FF3D","#FF00F4FF"],"type":0,"grWidth":0,"grHeight":0},"textTextureScale":0},{"viewId":1589055668321,"layerFullLocked":false,"layerHidden":false,"layerLocked":"false","maskRoundRectRadius":30,"border":"0","borderColor":"#00000000","opacity":"1.0","rotateAngle":"90.0","backgroundColor":"#00000000","xPoint":"931.48145","yPoint":"1.8518518","selected":"false","layoutParamsHeight":"-2","layoutParamsWidth":"-2","rootLayoutHeight":"222","rootLayoutWidth":"843","textPadding":0,"viewType":"textView","zoomScale":"0.54","text":"بیان بعد از نمازِ فجر","textAlignment":"textCenterAlignment","textVerticalAlignment":"textTopAlignment","typeFaceName":"Al_Mushaf","typeFaceType":"urdu","textSize":"40","textSizeSP":120,"textColor":"#FF000000","flipHorizontal":"1.0","flipVertical":"1.0","stroke":"17.0","strokeColor":"#FFFFFFFF","shadowRadius":"0.8","shadowColor":"#FF6B6B6B","shadowX":"1.0","shadowY":"4.0","lineSpacing":"1.0","wordSpacing":0.0010000000474974513,"wordArc":0,"textBold":false,"textItalic":false,"textUnderline":false,"textEmboss":false,"textTextureScale":0},{"viewId":1589055734765,"layerFullLocked":false,"layerHidden":false,"layerLocked":"false","maskRoundRectRadius":30,"border":"0","borderColor":"#00000000","opacity":"1.0","rotateAngle":"90.0","backgroundColor":"#00000000","xPoint":"1172.2222","yPoint":"494.44443","selected":"false","layoutParamsHeight":"-2","layoutParamsWidth":"-2","rootLayoutHeight":"369","rootLayoutWidth":"323","textPadding":0,"viewType":"textView","zoomScale":"0.54","text":"حضرت\nمولانا","textAlignment":"textLeftAlignment","textVerticalAlignment":"textTopAlignment","typeFaceName":"Mehr Nastaliq Web","typeFaceType":"urdu","textSize":"43","textSizeSP":129,"textColor":"#FF000000","flipHorizontal":"1.0","flipVertical":"1.0","stroke":"21.0","strokeColor":"#FFFFFFFF","shadowRadius":"0.8","shadowColor":"#FF6B6B6B","shadowX":"1.0","shadowY":"4.0","lineSpacing":"0.6","wordSpacing":0.0010000000474974513,"wordArc":0,"textBold":false,"textItalic":false,"textUnderline":false,"textEmboss":false,"textTextureScale":0},{"viewId":1589055776273,"layerFullLocked":false,"layerHidden":false,"layerLocked":"false","maskRoundRectRadius":30,"border":"0","borderColor":"#00000000","opacity":"1.0","rotateAngle":"90.0","backgroundColor":"#00000000","xPoint":"359.25925","yPoint":"505.55554","selected":"false","layoutParamsHeight":"-2","layoutParamsWidth":"-2","rootLayoutHeight":"381","rootLayoutWidth":"805","textPadding":0,"viewType":"textView","zoomScale":"0.54","text":"عـطـا اللہ شاہ","textAlignment":"textCenterAlignment","textVerticalAlignment":"textTopAlignment","typeFaceName":"urdu-emad-nastaleeq-regular","typeFaceType":"urdu","textSize":"72","textSizeSP":216,"textColor":"#FF000000","flipHorizontal":"1.0","flipVertical":"1.0","stroke":"21.0","strokeColor":"#FFFFFFFF","shadowRadius":"0.8","shadowColor":"#FF6B6B6B","shadowX":"1.0","shadowY":"4.0","lineSpacing":"0.6","wordSpacing":0.0010000000474974513,"wordArc":0,"textBold":false,"textItalic":false,"textUnderline":false,"textEmboss":false,"gradient":{"angle":90,"colors":["#FF8BC7FF","#FF2B32B2"],"type":0,"grWidth":0,"grHeight":0},"textTextureScale":0},{"viewId":1589055947500,"layerFullLocked":false,"layerHidden":false,"layerLocked":"false","maskRoundRectRadius":30,"border":"0","borderColor":"#00000000","opacity":"1.0","rotateAngle":"90.0","backgroundColor":"#00000000","xPoint":"146.2963","yPoint":"475.9259","selected":"false","layoutParamsHeight":"-2","layoutParamsWidth":"-2","rootLayoutHeight":"356","rootLayoutWidth":"280","textPadding":14,"viewType":"textView","zoomScale":"0.54","text":"رحمۃ اللہ\nبخاری","textAlignment":"textLeftAlignment","textVerticalAlignment":"textTopAlignment","typeFaceName":"Mehr Nastaliq Web","typeFaceType":"urdu","textSize":"37","textSizeSP":111,"textColor":"#FF000000","flipHorizontal":"1.0","flipVertical":"1.0","stroke":"21.0","strokeColor":"#FFFFFFFF","shadowRadius":"0.8","shadowColor":"#FF6B6B6B","shadowX":"1.0","shadowY":"4.0","lineSpacing":"0.6","wordSpacing":0.0010000000474974513,"wordArc":0,"textBold":false,"textItalic":false,"textUnderline":false,"textEmboss":false,"textTextureScale":0},{"viewId":1589056050652,"layerFullLocked":false,"layerHidden":false,"layerLocked":"false","maskRoundRectRadius":0,"border":"13","borderColor":"#FF886E00","opacity":"1.0","rotateAngle":"90.0","backgroundColor":"#FFFFFC00","xPoint":"-53.7037","yPoint":"894.4444","selected":"false","layoutParamsHeight":"-2","layoutParamsWidth":"-2","rootLayoutHeight":"178","rootLayoutWidth":"1205","textPadding":0,"viewType":"textView","zoomScale":"0.54","text":" ","textAlignment":"textCenterAlignment","textVerticalAlignment":"textTopAlignment","typeFaceName":"Mehr Nastaliq Web","typeFaceType":"urdu","textSize":"18","textSizeSP":54,"textColor":"#FFFF0000","flipHorizontal":"1.0","flipVertical":"1.0","stroke":"0.0","strokeColor":"#FF696969","shadowRadius":"0.0","shadowColor":"#FF444444","shadowX":"5.0","shadowY":"5.0","lineSpacing":"1.0","wordSpacing":0.0010000000474974513,"wordArc":0,"textBold":false,"textItalic":false,"textUnderline":false,"textEmboss":false,"textTextureScale":0},{"viewId":1589056137125,"layerFullLocked":false,"layerHidden":false,"layerLocked":"false","maskRoundRectRadius":30,"border":"0","borderColor":"#00000000","opacity":"1.0","rotateAngle":"90.0","backgroundColor":"#00000000","xPoint":"-3.7037036","yPoint":"907.40735","selected":"false","layoutParamsHeight":"-2","layoutParamsWidth":"-2","rootLayoutHeight":"160","rootLayoutWidth":"1144","textPadding":0,"viewType":"textView","zoomScale":"0.54","text":"مزید ویڈیوز کیلئے ہمارا چینل سبسکرائب کریں","textAlignment":"textCenterAlignment","textVerticalAlignment":"textTopAlignment","typeFaceName":"Mehr Nastaliq Web","typeFaceType":"urdu","textSize":"28","textSizeSP":84,"textColor":"#FF111111","flipHorizontal":"1.0","flipVertical":"1.0","stroke":"0.0","strokeColor":"#FF696969","shadowRadius":"0.0","shadowColor":"#FF444444","shadowX":"5.0","shadowY":"5.0","lineSpacing":"1.0","wordSpacing":0.0010000000474974513,"wordArc":0,"textBold":false,"textItalic":false,"textUnderline":false,"textEmboss":false,"textTextureScale":0},{"viewId":1589056261062,"layerFullLocked":false,"layerHidden":false,"layerLocked":"false","maskRoundRectRadius":30,"border":"0","borderColor":"#00000000","opacity":"1.0","rotateAngle":"90.0","backgroundColor":"#00000000","xPoint":"540.7407","yPoint":"-35.185184","selected":"false","layoutParamsHeight":"-2","layoutParamsWidth":"-2","rootLayoutHeight":"263","rootLayoutWidth":"564","textPadding":0,"viewType":"textView","zoomScale":"0.54","text":" 15رمضان","textAlignment":"textCenterAlignment","textVerticalAlignment":"textTopAlignment","typeFaceName":"nafees-nastaleeq-regular","typeFaceType":"urdu","textSize":"40","textSizeSP":120,"textColor":"#FF000000","flipHorizontal":"1.0","flipVertical":"1.0","stroke":"17.0","strokeColor":"#FFFFFFFF","shadowRadius":"0.8","shadowColor":"#FF6B6B6B","shadowX":"1.0","shadowY":"4.0","lineSpacing":"1.0","wordSpacing":0.0010000000474974513,"wordArc":0,"textBold":true,"textItalic":false,"textUnderline":false,"textEmboss":false,"gradient":{"angle":90,"colors":["#e52d27","#b31217"],"type":0,"grWidth":0,"grHeight":0},"textTextureScale":0},{"viewId":1589056397837,"layerFullLocked":false,"layerHidden":false,"layerLocked":"false","maskRoundRectRadius":30,"border":"11","borderColor":"#FF888888","opacity":"1.0","rotateAngle":"90.0","backgroundColor":"#FFE8E8E8","xPoint":"53.841278","yPoint":"44.405178","selected":"false","layoutParamsHeight":"-2","layoutParamsWidth":"-2","rootLayoutHeight":"106","rootLayoutWidth":"465","textPadding":7,"viewType":"textView","zoomScale":"0.54","text":"      Subscribe","textAlignment":"textCenterAlignment","textVerticalAlignment":"textTopAlignment","typeFaceName":"Roboto-Regular","typeFaceType":"all","textSize":"20","textSizeSP":60,"textColor":"#FFFF0000","flipHorizontal":"1.0","flipVertical":"1.0","stroke":"0.0","strokeColor":"#FF696969","shadowRadius":"0.0","shadowColor":"#FF444444","shadowX":"5.0","shadowY":"5.0","lineSpacing":"1.0","wordSpacing":0.0010000000474974513,"wordArc":0,"textBold":false,"textItalic":false,"textUnderline":false,"textEmboss":false,"textTextureScale":0},{"viewId":1589056356028,"layerFullLocked":false,"layerHidden":false,"layerLocked":"false","maskRoundRectRadius":30,"border":"0","borderColor":"#00000000","opacity":"1.0","rotateAngle":"90.0","backgroundColor":"#00000000","xPoint":"41.629852","yPoint":"20.537394","selected":"false","layoutParamsHeight":"-2","layoutParamsWidth":"-2","rootLayoutHeight":"148","rootLayoutWidth":"148","textPadding":0,"viewType":"shapeView","zoomScale":"0.54","text":"Ö","textAlignment":"textCenterAlignment","textVerticalAlignment":"textTopAlignment","typeFaceName":"social_media.otf","typeFaceType":"icon","textSize":"18","textSizeSP":54,"textColor":"#FFFF0000","flipHorizontal":"1.0","flipVertical":"1.0","stroke":"0.0","strokeColor":"#FF696969","shadowRadius":"0.0","shadowColor":"#FF444444","shadowX":"5.0","shadowY":"5.0","lineSpacing":"1.0","wordSpacing":0.0010000000474974513,"wordArc":0,"textBold":false,"textItalic":false,"textUnderline":false,"textEmboss":false,"textTextureScale":0,"shapeViewVer":2}],"project_files":[".images\/1589055539388.imagitorImage",".images\/1589055576297.imagitorImage"],"project_description":"روزے کے روحانی ثمراتبیان بعد از نمازِ فجرحضرت\nمولاناعـطـا اللہ شاہرحمۃ اللہ\nبخاری مزید ویڈیوز کیلئے ہمارا چینل سبسکرائب کریں 15رمضان      SubscribeÖ"}